Workbook

Sheet Report
A1: LLM HOSTING COST ESTIMATE - EXECUTIVE SUMMARY
A2: ="Prepared from published US list prices, August 2026. Model: "&Simple_Calc!$B$6&" | Cloud: "&Calculator!$B$37 -> Prepared from published US list prices, August 2026. Model: Large - top-tier assistant, complex reasoning and long documents | Cloud: Microsoft Azure
A4: 1. WHAT WAS ASKED FOR
A5: Model | B5: =Simple_Calc!$B$6 -> Large - top-tier assistant, complex reasoning and long documents
A6: Size and quality setting | B6: =TEXT(Calculator!$D$6,"#,##0")&" billion parameters at "&Calculator!$D$7 -> 70 billion parameters at FP8 / INT8 - balanced
A7: Expected traffic | B7: =IF(Inference!$B$6=Rates!$I$46,"Not specified - sized on memory only",TEXT(Inference!$B$7,"#,##0")&" requests/month ("&TEXT(Inference!$B$8,"#,##0")&" in / "&TEXT(Inference!$B$9,"#,##0")&" out tokens each)") -> 500,000 requests/month (800 in / 400 out tokens each)
A8: Availability | B8: =TEXT(Calculator!$D$17,"#,##0")&" hours/day over "&TEXT(Calculator!$D$18,"#,##0.0")&" days/month = "&TEXT(Calculator!$B$45,"#,##0")&" billed hours" -> 24 hours/day over 30.4 days/month = 730 billed hours
A9: Region and pricing basis | B9: =Calculator!$B$14&" | "&Calculator!$D$16 -> US (baseline) | On-demand (pay as you go)
A11: 2. RECOMMENDATION
A12: Cloud | B12: =Calculator!$B$37 -> Microsoft Azure
A13: Machine type | B13: =Calculator!$B$36 -> Standard_NC40ads_H100_v5
A14: GPU | B14: =TEXT(Calculator!$B$39,"#,##0")&" x "&Calculator!$B$38&" ("&TEXT(Calculator!$B$40,"#,##0")&" GB GPU memory per machine)" -> 1 x NVIDIA H100 NVL (94 GB GPU memory per machine)
A15: Machines required | B15: =TEXT(Calculator!$D$9,"#,##0") -> 1 | C15: =IF(Inference!$B$23>1,"Set by throughput: the peak load needs this many to keep up","One machine covers the load") -> One machine covers the load
A16: GPU memory the model needs | B16: =TEXT(Calculator!$B$10,"#,##0")&" GB per copy" -> 91 GB per copy | C16: Weights plus headroom for the conversation cache
A17: Basis for the choice | B17: ="Cheapest option that both fits in memory and meets the peak token rate" -> Cheapest option that both fits in memory and meets the peak token rate
A19: 3. MONTHLY COST | C19: Share of total
A20: GPU compute | B20: =Calculator!$B$48 -> 5095.9584 | C20: =IFERROR(B20/$B$25,0) -> 0.41559768
A21: Disk storage | B21: =Calculator!$B$49 -> 40.5 | C21: =IFERROR(B21/$B$25,0) -> 0.003302952
A22: Data transfer out | B22: =Calculator!$B$50 -> 165.3 | C22: =IFERROR(B22/$B$25,0) -> 0.013480938
A23: Managed platform | B23: =Calculator!$B$51 -> 0 | C23: =IFERROR(B23/$B$25,0) -> 0
A24: Support and labour | B24: =Calculator!$B$52 -> 6960 | C24: =IFERROR(B24/$B$25,0) -> 0.56761843
A25: TOTAL PER MONTH | B25: =Calculator!$B$53 -> 12261.758
A26: TOTAL PER YEAR | B26: =Calculator!$B$54 -> 147141.1
A28: 4. GOOGLE CLOUD vs MICROSOFT AZURE
A29: Google Cloud, best option | B29: =Comparison!$B$5 -> g2-standard-96 | C29: =Comparison!$B$22 -> 13083.169
A30: Microsoft Azure, best option | B30: =Comparison!$C$5 -> Standard_NC40ads_H100_v5 | C30: =Comparison!$C$22 -> 12261.758
A31: Verdict | B31: =Comparison!$B$25 -> Microsoft Azure saves about $821 per month (6.3% less)
A33: 5. CAPACITY AND UNIT ECONOMICS
A34: Tokens per second, one machine | B34: =IF(Inference!$B$6=Rates!$I$46,"not sized",TEXT(Inference!$B$22,"#,##0")) -> 624 | C34: Bandwidth model, accurate to roughly a factor of two
A35: Peak tokens per second needed | B35: =IF(Inference!$B$6=Rates!$I$46,"not specified",TEXT(Inference!$B$16,"#,##0")) -> 274
A36: Spare capacity at peak | B36: =IF(Inference!$B$6=Rates!$I$46,"n/a",TEXT(Inference!$B$26,"0.0%")) -> 127.8%
A37: Speed one user would see | B37: =IF(Inference!$B$6=Rates!$I$46,"n/a",TEXT(Inference!$B$25,"#,##0")&" tokens/sec"&IF(Inference!$B$25<10," - slow"," - acceptable")) -> 39 tokens/sec - acceptable
A38: Cost per million output tokens | B38: =IF(Inference!$B$6=Rates!$I$46,"n/a - traffic not specified",TEXT(Inference!$B$31,"$#,##0.00")) -> $61.31 | C38: Compare directly against a pay-per-token API quote
A39: Cost per 1,000 requests | B39: =IF(Inference!$B$6=Rates!$I$46,"n/a",TEXT(Inference!$B$32,"$#,##0.00")) -> $24.52
A40: Pay-per-token alternative | B40: =IF(Inference!$B$7<=0,"not compared - traffic not specified",Calculator!$B$60&" at $"&TEXT(Calculator!$B$70,"#,##0")&"/month") -> Gemini 3.5 Flash-Lite at $2,940/month | C40: Same traffic, no machines to run. See the Comparison tab for the cheapest on each cloud
A41: Cheaper route on these numbers | B41: =IF(Inference!$B$7<=0,"n/a",IF(Calculator!$B$70<Calculator!$B$53,"Pay per token - saves $"&TEXT(Calculator!$B$53-Calculator!$B$70,"#,##0")&"/month","Self-host - saves $"&TEXT(Calculator!$B$70-Calculator!$B$53,"#,##0")&"/month")) -> Pay per token - saves $9,322/month
A42: Support level applied | B42: =Calculator!$B$128&" - "&TEXT(Calculator!$B$31,"#,##0")&" engineer hours/month at $"&TEXT(Calculator!$B$33,"#,##0")&"/hour" -> Medium - 60 engineer hours/month at $116/hour
A44: 6. WHAT COULD MOVE THIS NUMBER
A45: ="Price confidence for the chosen machine: "&IF(Calculator!$B$122=0,"n/a",INDEX(GPU_Price_List!$Q$5:$Q$35,Calculator!$B$121))&IF(Calculator!$B$122=0,"",IF(ISNUMBER(SEARCH("estimate",INDEX(GPU_Price_List!$Q$5:$Q$35,Calculator!$B$121)))," - CONFIRM THIS RATE BEFORE COMMITTING BUDGET","")) -> Price confidence for the chosen machine: Published list price
A46: ="Throughput assumes a batching gain of "&TEXT(Rates!$B$108,"#,##0")&"x from a modern serving stack. A naive setup would need several times more machines." -> Throughput assumes a batching gain of 16x from a modern serving stack. A naive setup would need several times more machines.
A47: ="Machines are sized for peak traffic ("&TEXT(Inference!$B$10,"#,##0.0")&"x average), so spare capacity sits idle most of the month." -> Machines are sized for peak traffic (3.0x average), so spare capacity sits idle most of the month.
A48: ="Idle time is billed in full. Reducing the "&TEXT(Calculator!$D$17,"#,##0")&" hours/day is usually the single largest saving available." -> Idle time is billed in full. Reducing the 24 hours/day is usually the single largest saving available.
A49: ="Excluded: load balancers, monitoring, backups, cloud support plans, one-off setup work, taxes, and any negotiated discount your organisation already holds." -> Excluded: load balancers, monitoring, backups, cloud support plans, one-off setup work, taxes, and any negotiated discount your organisation already holds.
A50: ="GPU quota starts at zero on both clouds. Approval to launch these machines can take days to weeks." -> GPU quota starts at zero on both clouds. Approval to launch these machines can take days to weeks.
A52: Planning estimate, not a quote. Figures are US-region list prices and a bandwidth-based throughput model; measure real throughput before committing capacity. Full workings and sources are in this workbook.

Sheet Simple_Calc
A1: Quick Estimate - three questions
A2: Answer the three questions below by clicking each yellow box and picking from the list. Your estimate appears underneath.
A3: No technical knowledge needed. Everything else is worked out for you on the Calculator tab.
A5: 1. How big is the AI model you want to run?
B6: Large - top-tier assistant, complex reasoning and long documents | C6: If you are not sure, pick Large - it is the most common choice for a serious assistant.
A8: 2. How much use will it get?
B9: A whole department, running around the clock | C9: This sets how many hours a month you pay for - usually the biggest lever on the bill.
A11: 3. What matters most to you?
B12: A balance of cost and reliability | C12: Lowest cost accepts machines that can be interrupted. Reliability commits to a year and adds a managed platform.
A14: WHAT THIS MEANS - these values are sent to the Calculator tab
A15: Setting on the Calculator tab | B15: Comes from | C15: Value sent
A16: Model size (billions of parameters) | B16: Question 1 | C16: =INDEX(Rates!$B$89:$B$92,MATCH($B$6,Rates!$A$89:$A$92,0)) -> 70
A17: Disk storage per copy (GB) | B17: Question 1 | C17: =INDEX(Rates!$C$89:$C$92,MATCH($B$6,Rates!$A$89:$A$92,0)) -> 500
A18: Hours running per day | B18: Question 2 | C18: =INDEX(Rates!$B$95:$B$98,MATCH($B$9,Rates!$A$95:$A$98,0)) -> 24
A19: Days running per month | B19: Question 2 | C19: =INDEX(Rates!$C$95:$C$98,MATCH($B$9,Rates!$A$95:$A$98,0)) -> 30.42
A20: Minimum copies of the model | B20: Question 2 | C20: =INDEX(Rates!$D$95:$D$98,MATCH($B$9,Rates!$A$95:$A$98,0)) -> 1
A21: Data sent out to users (GB per month) | B21: Question 2 | C21: =INDEX(Rates!$E$95:$E$98,MATCH($B$9,Rates!$A$95:$A$98,0)) -> 2000
A22: Precision / quantization | B22: Question 3 | C22: =INDEX(Rates!$B$101:$B$103,MATCH($B$12,Rates!$A$101:$A$103,0)) -> FP8 / INT8 - balanced
A23: Pricing model | B23: Question 3 | C23: =INDEX(Rates!$C$101:$C$103,MATCH($B$12,Rates!$A$101:$A$103,0)) -> On-demand (pay as you go)
A24: Managed AI platform | B24: Question 3 | C24: =INDEX(Rates!$D$101:$D$103,MATCH($B$12,Rates!$A$101:$A$103,0)) -> No - plain virtual machines
A26: Support level, cloud choice, region and disk type are not asked here. Support is recommended automatically from the model size, the cloud is set to compare both, and the rest keep sensible defaults. Change any of them on the Calculator tab.
A29: YOUR ESTIMATE
A30: GPU memory your model needs (GB) | B30: =Calculator!$B$10 -> 91
A31: Cheapest machine that fits | B31: =Calculator!$B$36 -> Standard_NC40ads_H100_v5
A32: On which cloud | B32: =Calculator!$B$37 -> Microsoft Azure
A33: Hours you pay for each month | B33: =Calculator!$B$45 -> 730.08
A34: Machines being paid for | B34: =Calculator!$D$9 -> 1 | C34: =IF(Calculator!$D$9>$C$20,"Raised from "&$C$20&" because the traffic on the Inference tab needs "&Inference!$B$23&" machines to keep up","Matches the minimum above") -> Matches the minimum above
A36: Machines and storage | B36: =Calculator!$B$48+Calculator!$B$49+Calculator!$B$50+Calculator!$B$51 -> 5301.7584
A37: People to support it | B37: =Calculator!$B$52 -> 6960
A38: TOTAL PER MONTH | B38: =Calculator!$B$53 -> 12261.758
A39: TOTAL PER YEAR | B39: =Calculator!$B$54 -> 147141.1
A41: In plain words | B41: =IF(Calculator!$B$122=0,"No single machine is big enough for a model this size at this quality setting. Try answering ""Lowest possible cost"" to question 3, or pick a smaller model in question 1.","Running a "&LOWER(LEFT($B$6,FIND(" ",$B$6)-1))&" model this way costs about $"&TEXT(Calculator!$B$53,"#,##0")&" a month, of which $"&TEXT(Calculator!$B$52,"#,##0")&" is the people who look after it and $"&TEXT(Calculator!$B$53-Calculator!$B$52,"#,##0")&" is the cloud bill. That is $"&TEXT(Calculator!$B$54,"#,##0")&" over a year.") -> Running a large model this way costs about $12,262 a month, of which $6,960 is the people who look after it and $5,302 is the cloud bill. That is $147,141 over a year.
A45: Before you use this number:
A46: - It is a planning estimate from published US list prices, not a quote.
A47: - Turning the machines off when nobody is using them is the single biggest saving available - that is question 2.
A48: - The Comparison tab shows Google Cloud and Azure side by side for the same answers.
A49: - If three questions are not enough, switch the Calculator tab to Expert mode and edit any value directly.
A51: OR DON'T RUN IT YOURSELF - pay per token instead
A52: Cheapest hosted model for this traffic | B52: =IFERROR(INDEX(Rates!$A$114:$A$134,MATCH(MIN(Rates!$I$114:$I$134),Rates!$I$114:$I$134,0)),"-") -> Gemini 2.5 Flash-Lite | C52: Chosen across both clouds on price alone. Pick a specific model on the Calculator tab, step 7.
A53: Runs on | B53: =IFERROR(INDEX(Rates!$B$114:$B$134,MATCH(MIN(Rates!$I$114:$I$134),Rates!$I$114:$I$134,0)),"-") -> Google Cloud
A54: Token charges per month | B54: =MIN(Rates!$I$114:$I$134) -> 120
A55: People to run it | B55: =Calculator!$B$69 -> 2320
A56: TOTAL PER MONTH | B56: =MIN(Rates!$I$114:$I$134)+Calculator!$B$69 -> 2440
A58: Which should we do? | B58: =IF(Inference!$B$7<=0,"Set your expected traffic on the Inference tab to see this comparison.",IF($B$56<$B$38,"Paying per token looks cheaper for this much traffic - about $"&TEXT($B$38-$B$56,"#,##0")&" a month less, and far less to look after. Running your own machines usually only wins once traffic is much heavier, or when the data cannot leave your control.","Running your own machines looks cheaper here - about $"&TEXT($B$56-$B$38,"#,##0")&" a month less - because there is enough traffic to keep them busy.")) -> Paying per token looks cheaper for this much traffic - about $9,822 a month less, and far less to look after. Running your own machines usually only wins once traffic is much heavier, or when the data cannot leave your control.

Sheet Calculator
A1: LLM Hosting Cost Calculator - Google Cloud vs Microsoft Azure
A2: Every yellow box on this tab is editable and takes effect immediately. Rows marked >> start out blank and borrow their value from the Simple_Calc tab until you type over them. Your estimate builds itself in step 6.
A3: Nothing here connects to a live account - it is a planning estimate using published US list prices from August 2026.
A4: Rows marked >> | B4: leave blank = use Simple_Calc | C4: Type anything into a yellow box and it takes over that row straight away. Clear the box to hand the row back to Simple_Calc. Every other row is yours as normal. | D4: Value in use | E4: Coming from
A5: STEP 1 - YOUR MODEL
A6: >> Model size (billions of parameters) | C6: e.g. 8 for an 8B model, 70 for a 70B model, 671 for DeepSeek-size | D6: =IF($B$6="",Simple_Calc!$C$16,$B$6) -> 70 | E6: =IF($B$6="","Simple_Calc","your entry") -> Simple_Calc
A7: >> Precision / quantization | C7: INT4 needs a quarter of the memory of FP16. | D7: =IF($B$7="",Simple_Calc!$C$22,$B$7) -> FP8 / INT8 - balanced | E7: =IF($B$7="","Simple_Calc","your entry") -> Simple_Calc
A8: Extra memory headroom (%) | B8: 0.3 | C8: Covers the conversation cache and working memory. 30% is a safe default.
A9: >> How many copies of the model to run | C9: Raised automatically if the Inference tab says the traffic needs more machines. | D9: =MAX(IF($B$9="",Simple_Calc!$C$20,$B$9),$B$130) -> 1 | E9: =IF($B$9="","Simple_Calc","your entry") -> Simple_Calc
A10: GPU memory needed for ONE copy (GB) | B10: =ROUNDUP($D$6*INDEX(Rates!$B$39:$B$41,MATCH($D$7,Rates!$A$39:$A$41,0))*(1+B8),0) -> 91 | C10: Calculated for you - this decides which machines are big enough.
A12: STEP 2 - WHERE TO RUN IT
A13: Cloud provider | B13: Compare both | C13: Choose one, or 'Compare both' to let the sheet pick the cheaper.
A14: Region | B14: US (baseline) | C14: US is cheapest. Other regions add a rough uplift - see the Rates tab.
A15: Which machine? | B15: Auto - cheapest that fits | C15: Leave on Auto and the sheet finds the cheapest one that fits.
A16: >> Pricing model | C16: Spot is cheapest but can be interrupted. Commitment needs a 1-year contract. | D16: =IF($B$16="",Simple_Calc!$C$23,$B$16) -> On-demand (pay as you go) | E16: =IF($B$16="","Simple_Calc","your entry") -> Simple_Calc
A17: >> Hours running per day | C17: 24 means always on. 8 means office hours only. | D17: =IF($B$17="",Simple_Calc!$C$18,$B$17) -> 24 | E17: =IF($B$17="","Simple_Calc","your entry") -> Simple_Calc
A18: >> Days running per month | C18: 30.42 is the average month. Use 22 for weekdays only. | D18: =IF($B$18="",Simple_Calc!$C$19,$B$18) -> 30.42 | E18: =IF($B$18="","Simple_Calc","your entry") -> Simple_Calc
A20: STEP 3 - STORAGE AND DATA
A21: >> Disk storage per copy (GB) | C21: Room for the model files, logs and scratch space. | D21: =IF($B$21="",Simple_Calc!$C$17,$B$21) -> 500 | E21: =IF($B$21="","Simple_Calc","your entry") -> Simple_Calc
A22: Disk type | B22: Balanced SSD (recommended) | C22: Balanced SSD suits almost everyone.
A23: >> Data sent out to users (GB per month) | C23: Only data leaving the cloud is charged. Text answers are small; audio and video are not. | D23: =IF($B$23="",Simple_Calc!$C$21,$B$23) -> 2000 | E23: =IF($B$23="","Simple_Calc","your entry") -> Simple_Calc
A25: STEP 4 - MANAGED PLATFORM
A26: >> Use a managed AI platform? | C26: Vertex AI or Azure ML do the plumbing for you and add about 25% to compute. | D26: =IF($B$26="",Simple_Calc!$C$24,$B$26) -> No - plain virtual machines | E26: =IF($B$26="","Simple_Calc","your entry") -> Simple_Calc
A28: STEP 5 - SUPPORT AND LABOUR (the people who keep it running)
A29: Recommended support level | B29: =IF($D$6<=Rates!$B$85,IF($D$6<=Rates!$B$84,Rates!$A$80,Rates!$A$81),Rates!$A$82) -> Medium | C29: Based on your model size. Low up to 13B, Medium up to 70B, High above that.
A30: Support level to use | B30: Use the recommendation | C30: Keep the recommendation, or override it with Low, Medium or High.
A31: Engineer hours per month | B31: =IF($B$32="",INDEX(Rates!$B$80:$B$82,MATCH($B$128,Rates!$A$80:$A$82,0)),$B$32) -> 60 | C31: Comes from the table on the Rates tab: Low 20, Medium 60, High 160 hours.
A32: Override the hours (optional) | C32: Leave this blank to use the table above. Type a number to use your own.
A33: Engineer cost per hour ($) | B33: 116 | C33: Your blended support rate.
A35: STEP 6 - YOUR ESTIMATE
A36: Recommended machine | B36: =IF($B$122=0,"none available",INDEX(GPU_Price_List!$H$5:$H$35,$B$121)) -> Standard_NC40ads_H100_v5
A37: Cloud | B37: =IF($B$122=0,"-",INDEX(GPU_Price_List!$C$5:$C$35,$B$121)) -> Microsoft Azure
A38: GPU | B38: =IF($B$122=0,"-",INDEX(GPU_Price_List!$D$5:$D$35,$B$121)) -> NVIDIA H100 NVL
A39: GPUs per machine | B39: =IF($B$122=0,0,INDEX(GPU_Price_List!$F$5:$F$35,$B$121)) -> 1
A40: Total GPU memory per machine (GB) | B40: =IF($B$122=0,0,INDEX(GPU_Price_List!$G$5:$G$35,$B$121)) -> 94
A41: vCPU per machine | B41: =IF($B$122=0,0,INDEX(GPU_Price_List!$I$5:$I$35,$B$121)) -> 40
A42: System RAM per machine (GB) | B42: =IF($B$122=0,0,INDEX(GPU_Price_List!$J$5:$J$35,$B$121)) -> 320
A43: US list price ($/hour) | B43: =IF($B$122=0,0,INDEX(GPU_Price_List!$K$5:$K$35,$B$121)) -> 6.98
A44: Your rate after region and pricing model ($/hour) | B44: =IF($B$122=0,0,INDEX(GPU_Price_List!$T$5:$T$35,$B$121)*$B$124) -> 6.98
A45: Hours billed per month | B45: =$D$17*$D$18 -> 730.08
A47: MONTHLY COST BREAKDOWN
A48: Compute - GPU machines | B48: =B44*B45*$D$9 -> 5095.9584 | C48: hourly rate x hours x number of copies
A49: Disk storage | B49: =IF($B$122=0,0,$D$21*$D$9*$B$125) -> 40.5 | C49: GB per copy x copies x price per GB
A50: Data transfer out (egress) | B50: =IF($B$122=0,0,IF($B$37=Rates!$A$46,$B$127,$B$126)) -> 165.3 | C50: Charged only on data leaving the cloud; each cloud has a free allowance
A51: Managed platform uplift | B51: =IF($D$26=Rates!$F$46,$B$48*IF($B$37=Rates!$A$45,Rates!$B$34,Rates!$B$35),0) -> 0 | C51: Zero unless you chose a managed platform in step 4
A52: Support and labour | B52: =$B$31*$B$33 -> 6960 | C52: =$B$31&" hours x $"&TEXT($B$33,"#,##0")&" per hour ("&$B$128&" support)" -> 60 hours x $116 per hour (Medium support)
A53: TOTAL ESTIMATED COST PER MONTH | B53: =SUM(B48:B52) -> 12261.758
A54: Same estimate per year | B54: =B53*12 -> 147141.1
A55: Cost per hour of service | B55: =IFERROR(B53/B45,0) -> 16.795089
A56: Speed check | B56: =IF($B$122=0,"-",IF(AND(INDEX(GPU_Price_List!$A$5:$A$35,$B$121)<=2,$B$39>=4),"Cheapest on memory, but it spreads your model over "&$B$39&" small GPUs. That is slower to answer and harder to set up than one large GPU - consider a higher tier if speed matters.",IF($B$39>=8,"This is a full "&$B$39&"-GPU machine. You pay for all "&$B$39&" GPUs even if the model only needs some of them.","Sensible fit - the model runs on "&$B$39&" GPU(s) of this class."))) -> Sensible fit - the model runs on 1 GPU(s) of this class.
A57: Status | B57: =IF($B$122=0,"No machine on the price list has enough GPU memory ("&$B$10&" GB) for the cloud you picked. Try INT4 in step 1, a smaller model, or set the cloud to Compare both.","Looks good. Remember these are US list prices - any discount you have negotiated will lower them.") -> Looks good. Remember these are US list prices - any discount you have negotiated will lower them.
A59: STEP 7 - OR DON'T HOST IT AT ALL: pay per token for a hosted model | C59: Uses the traffic you set on the Inference tab. Nothing here changes steps 1 to 6.
A60: Which hosted model? | B60: Gemini 3.5 Flash-Lite | C60: Gemini, GPT and Claude models running on Google Cloud or Azure.
A61: Runs on | B61: =INDEX(Rates!$B$114:$B$134,MATCH($B$60,Rates!$A$114:$A$134,0)) -> Google Cloud
A62: Model built by | B62: =INDEX(Rates!$C$114:$C$134,MATCH($B$60,Rates!$A$114:$A$134,0)) -> Google
A63: Price per 1M input tokens | B63: =INDEX(Rates!$D$114:$D$134,MATCH($B$60,Rates!$A$114:$A$134,0)) -> 0.3
A64: Price per 1M output tokens | B64: =INDEX(Rates!$E$114:$E$134,MATCH($B$60,Rates!$A$114:$A$134,0)) -> 2.5
A65: Input tokens per month | B65: =Inference!$B$7*Inference!$B$8 -> 400000000
A66: Output tokens per month | B66: =Inference!$B$7*Inference!$B$9 -> 200000000
A67: Token charges per month | B67: =$B$65/1000000*$B$63+$B$66/1000000*$B$64 -> 620
A68: Engineer hours per month to run it | B68: 20 | C68: Far less than self-hosting - no machines to keep alive. 20 is a fair default.
A69: Support and labour | B69: =$B$68*$B$33 -> 2320
A70: TOTAL PER MONTH - pay per token | B70: =$B$67+$B$69 -> 2940
A71: Same per year | B71: =$B$70*12 -> 35280
A72: Cost per million output tokens | B72: =IFERROR($B$67/($B$66/1000000),0) -> 3.1
A73: Self-hosting total from step 6 | B73: =$B$53 -> 12261.758
A74: Difference | B74: =$B$70-$B$53 -> -9321.7584
A75: Which way is cheaper? | B75: =IF(Inference!$B$7<=0,"Enter your expected traffic on the Inference tab and this section will fill in.",IF($B$122=0,"Self-hosting has no machine big enough for this model, so paying per token is the only option here at $"&TEXT($B$70,"#,##0")&" per month.",IF($B$70<$B$53,"Paying per token is cheaper by $"&TEXT($B$53-$B$70,"#,##0")&" per month ("&TEXT(1-$B$70/$B$53,"0%")&" less), and there are no machines to keep alive. Raise the requests figure on the Inference tab to find the volume where that reverses.","Self-hosting is cheaper by $"&TEXT($B$70-$B$53,"#,##0")&" per month ("&TEXT(1-$B$53/$B$70,"0%")&" less), because you are running enough volume to fill the machines you rent."))) -> Paying per token is cheaper by $9,322 per month (76% less), and there are no machines to keep alive. Raise the requests figure on the Inference tab to find the volume where that reverses.
A77: What is NOT in this estimate:
A78: - Load balancers, monitoring tools, logging, backups, snapshots and paid cloud support plans.
A79: - Traffic between zones inside a region (about $0.01/GB each way on Google Cloud; free on Azure).
A80: - Idle time. A GPU machine costs the same whether it is busy or doing nothing - this is the biggest source of waste.
A81: - Windows licences, third-party model licences, and the one-off project work to get set up in the first place.
A82: - Taxes, and any enterprise discount your organisation has negotiated.
A120: CALCULATION ENGINE - no need to read or change anything below this line
A121: Chosen row on the price list | B121: =IF($B$15=Rates!$G$45,IFERROR(MATCH($B$123,GPU_Price_List!$W$5:$W$35,0),0),IFERROR(MATCH($B$15,GPU_Price_List!$S$5:$S$35,0),0)) -> 24
A122: Is a valid machine selected? (1 = yes) | B122: =IF($B$15=Rates!$G$45,IF($B$123>=1000000000,0,1),IF($B$121=0,0,1)) -> 1
A123: Cheapest eligible rate, either cloud | B123: =MIN(GPU_Price_List!$W$5:$W$35) -> 6.980001
A124: Region uplift for the chosen cloud | B124: =IF($B$37=Rates!$A$45,INDEX(Rates!$B$21:$B$24,MATCH($B$14,Rates!$A$21:$A$24,0)),INDEX(Rates!$C$21:$C$24,MATCH($B$14,Rates!$A$21:$A$24,0))) -> 1
A125: Storage price per GB for the chosen cloud | B125: =IF($B$37=Rates!$A$45,INDEX(Rates!$B$6:$B$9,MATCH($B$22,Rates!$A$6:$A$9,0)),INDEX(Rates!$C$6:$C$9,MATCH($B$22,Rates!$A$6:$A$9,0))) -> 0.081
A126: Egress cost if Google Cloud | B126: =MAX(MIN($D$23,1024)-Rates!$B$13,0)*Rates!$B$14+MIN(MAX($D$23-1024,0),9216)*Rates!$B$15+MAX($D$23-10240,0)*Rates!$B$16 -> 230.12
A127: Egress cost if Microsoft Azure | B127: =MAX($D$23-Rates!$C$13,0)*Rates!$C$14 -> 165.3
A128: Support level in use | B128: =IF($B$30=Rates!$H$45,$B$29,$B$30) -> Medium
A129: Model weights size, no headroom (GB) | B129: =$D$6*INDEX(Rates!$B$39:$B$41,MATCH($D$7,Rates!$A$39:$A$41,0)) -> 70
A130: Machines the load needs (throughput) | B130: =IF($B$122=0,1,INDEX(GPU_Price_List!$AC$5:$AC$35,$B$121)) -> 1

Sheet Inference
A1: Inference sizing - how much traffic can it actually serve?
A2: The other tabs ask whether a model FITS on a machine. This one asks whether the machine is FAST ENOUGH, and works out how many machines your traffic needs.
A3: Fill in the yellow boxes. Turn the first one off and the rest of the workbook behaves exactly as before.
A5: 1. YOUR TRAFFIC
A6: Size the machines for this traffic? | B6: Yes - size the machines for this traffic | C6: Turn this off to go back to memory-only sizing.
A7: Requests per month | B7: 500000 | C7: A question, a summary, a completion - one round trip.
A8: Input tokens per request (the prompt) | B8: 800 | C8: Roughly 600 words. Add a lot if you paste in documents.
A9: Output tokens per request (the answer) | B9: 400 | C9: Roughly 300 words. This is the expensive half.
A10: Peak-to-average factor | B10: 3 | C10: Traffic is never flat. 3 means the busiest hour is 3x the average.
A12: 2. WHAT THAT DEMANDS
A13: Output tokens per month | B13: =$B$7*$B$9 -> 200000000
A14: Work per request in output-token equivalents | B14: =$B$9+$B$8/Rates!$B$110 -> 480 | C14: Prompt tokens are cheaper to process, so they count for less
A15: Average tokens per second needed | B15: =IFERROR($B$7*$B$14/(Calculator!$D$17*Calculator!$D$18*3600),0) -> 91.314194 | C15: Spread evenly over the hours you chose on the Calculator
A16: PEAK tokens per second needed | B16: =IF($B$6=Rates!$I$46,0,$B$15*$B$10) -> 273.94258 | C16: This is the number the machines are sized against
A18: 3. WHAT THE CHOSEN MACHINE DELIVERS
A19: Machine the Calculator picked | B19: =Calculator!$B$36 -> Standard_NC40ads_H100_v5
A20: GPUs x memory bandwidth (GB/s) | B20: =IF(Calculator!$B$122=0,0,INDEX(GPU_Price_List!$AA$5:$AA$35,Calculator!$B$121)) -> 3900 | C20: Generating a token means reading the whole model out of memory once
A21: Model weights to read per token (GB) | B21: =Calculator!$B$129 -> 70
A22: Output tokens per second, one machine | B22: =IF(Calculator!$B$122=0,0,INDEX(GPU_Price_List!$AB$5:$AB$35,Calculator!$B$121)) -> 624 | C22: With batching and utilisation from the Rates tab, section J
A23: Machines the peak load needs | B23: =Calculator!$B$130 -> 1
A24: Machines the estimate is using | B24: =Calculator!$D$9 -> 1 | C24: The greater of your copies and the machines the traffic needs
A25: Speed for a single user (tokens/sec) | B25: =IFERROR($B$20/$B$21*Rates!$B$109,0) -> 39 | C25: Around 20 or more feels like fast typing. Below 10 feels slow.
A26: Headroom at peak | B26: =IFERROR($B$22*$B$24/$B$16-1,0) -> 1.2778496 | C26: How much spare capacity is left when traffic peaks
A28: 4. UNIT ECONOMICS
A29: Total cost per month (from the Calculator) | B29: =Calculator!$B$53 -> 12261.758
A30: Million output tokens served per month | B30: =$B$13/1000000 -> 200
A31: Cost per million output tokens | B31: =IFERROR($B$29/$B$30,0) -> 61.308792 | C31: Compare this directly with a pay-per-token API price
A32: Cost per 1,000 requests | B32: =IFERROR($B$29/$B$7*1000,0) -> 24.523517
A33: Cost per request | B33: =IFERROR($B$29/$B$7,0) -> 0.024523517
A35: Verdict | B35: =IF($B$6=Rates!$I$46,"Inference sizing is switched off. The workbook is sizing on memory only.",IF(Calculator!$B$122=0,"No machine has enough memory for this model yet - fix that on the Calculator first.",IF($B$23>1,"This load needs "&$B$23&" of these machines to keep up at peak. "&"One machine generates about "&TEXT($B$22,"#,##0")&" tokens a second and the peak needs "&TEXT($B$16,"#,##0")&". The cost above already includes all "&$B$23&".","One machine is enough: it generates about "&TEXT($B$22,"#,##0")&" tokens a second against a peak need of "&TEXT($B$16,"#,##0")&"."))) -> One machine is enough: it generates about 624 tokens a second against a peak need of 274.
A39: How the throughput number is worked out, and where it is weakest:
A40: - Generating one token requires reading every weight in the model out of GPU memory. So tokens per second is roughly GPU memory bandwidth divided by model size, multiplied by the batching gain and the utilisation figure on the Rates tab.
A41: - That is a bandwidth model, not a benchmark. Real throughput also depends on the serving software, sequence lengths, and how evenly requests arrive. Treat it as accurate to within a factor of about two, and measure before you commit.
A42: - The batching gain of 16 assumes a modern server such as vLLM or TensorRT-LLM with continuous batching. A naive one-request-at-a-time setup is closer to 1, which changes the answer enormously.
A43: - Long prompts and long context windows grow the conversation cache, which eats memory and slows decode. This model does not capture that - raise the headroom percentage on the Calculator if you serve long context.
A44: - Cost per million tokens counts output tokens only, which is the convention most API price lists use.
A45: - Machines are sized on the peak, so the spare capacity sits idle most of the month. That is what the headroom row shows.

Sheet Comparison
A1: Side-by-side: Google Cloud vs Microsoft Azure
A2: Both columns answer the same question: what is the cheapest machine on that cloud that is big enough for the model set up on the Calculator tab? Change the Calculator and this updates.
A4: What we are comparing | B4: Google Cloud | C4: Microsoft Azure | D4: Which is cheaper
A5: Cheapest machine that fits | B5: =IF($B$62=0,"-",INDEX(GPU_Price_List!$H$5:$H$35,$B$60)) -> g2-standard-96 | C5: =IF($B$63=0,"-",INDEX(GPU_Price_List!$H$5:$H$35,$B$61)) -> Standard_NC40ads_H100_v5
A6: GPU | B6: =IF($B$62=0,"-",INDEX(GPU_Price_List!$D$5:$D$35,$B$60)) -> NVIDIA L4 | C6: =IF($B$63=0,"-",INDEX(GPU_Price_List!$D$5:$D$35,$B$61)) -> NVIDIA H100 NVL
A7: GPUs per machine | B7: =IF($B$62=0,0,INDEX(GPU_Price_List!$F$5:$F$35,$B$60)) -> 8 | C7: =IF($B$63=0,0,INDEX(GPU_Price_List!$F$5:$F$35,$B$61)) -> 1
A8: Total GPU memory (GB) | B8: =IF($B$62=0,0,INDEX(GPU_Price_List!$G$5:$G$35,$B$60)) -> 192 | C8: =IF($B$63=0,0,INDEX(GPU_Price_List!$G$5:$G$35,$B$61)) -> 94 | D8: Must be at least the memory the model needs
A9: vCPU | B9: =IF($B$62=0,0,INDEX(GPU_Price_List!$I$5:$I$35,$B$60)) -> 96 | C9: =IF($B$63=0,0,INDEX(GPU_Price_List!$I$5:$I$35,$B$61)) -> 40
A10: System RAM (GB) | B10: =IF($B$62=0,0,INDEX(GPU_Price_List!$J$5:$J$35,$B$60)) -> 384 | C10: =IF($B$63=0,0,INDEX(GPU_Price_List!$J$5:$J$35,$B$61)) -> 320
A11: US list price ($/hour) | B11: =IF($B$62=0,0,INDEX(GPU_Price_List!$K$5:$K$35,$B$60)) -> 8.0033 | C11: =IF($B$63=0,0,INDEX(GPU_Price_List!$K$5:$K$35,$B$61)) -> 6.98
A12: Your rate after region and pricing model ($/hour) | B12: =IF($B$62=0,0,INDEX(GPU_Price_List!$T$5:$T$35,$B$60)*$B$64) -> 8.0033 | C12: =IF($B$63=0,0,INDEX(GPU_Price_List!$T$5:$T$35,$B$61)*$B$65) -> 6.98
A13: Hours billed per month | B13: =Calculator!$B$45 -> 730.08 | C13: =Calculator!$B$45 -> 730.08
A14: Copies of the model | B14: =Calculator!$D$9 -> 1 | C14: =Calculator!$D$9 -> 1
A16: MONTHLY COST
A17: Compute | B17: =B12*B13*B14 -> 5843.0493 | C17: =C12*C13*C14 -> 5095.9584
A18: Disk storage | B18: =IF($B$62=0,0,Calculator!$D$21*Calculator!$D$9*INDEX(Rates!$B$6:$B$9,MATCH(Calculator!$B$22,Rates!$A$6:$A$9,0))) -> 50 | C18: =IF($B$63=0,0,Calculator!$D$21*Calculator!$D$9*INDEX(Rates!$C$6:$C$9,MATCH(Calculator!$B$22,Rates!$A$6:$A$9,0))) -> 40.5 | D18: Azure Premium SSD v2 is cheaper per GB than Google's Balanced disk
A19: Data transfer out | B19: =IF($B$62=0,0,Calculator!$B$126) -> 230.12 | C19: =IF($B$63=0,0,Calculator!$B$127) -> 165.3 | D19: Azure includes 100 GB free per month; Google Cloud includes 1 GB
A20: Managed platform uplift | B20: =IF(Calculator!$D$26=Rates!$F$46,B17*Rates!$B$34,0) -> 0 | C20: =IF(Calculator!$D$26=Rates!$F$46,C17*Rates!$B$35,0) -> 0
A21: Support and labour | B21: =Calculator!$B$52 -> 6960 | C21: =Calculator!$B$52 -> 6960 | D21: Same either way - the people cost does not depend on which cloud you pick
A22: TOTAL PER MONTH | B22: =SUM(B17:B21) -> 13083.169 | C22: =SUM(C17:C21) -> 12261.758
A23: TOTAL PER YEAR | B23: =B22*12 -> 156998.03 | C23: =C22*12 -> 147141.1
A25: Cheaper option | B25: =IF(AND($B$62=0,$B$63=0),"Neither cloud has a single machine with enough GPU memory. Use INT4, a smaller model, or plan on splitting the model across several machines.",IF($B$62=0,"Only Microsoft Azure has a machine big enough for this model.",IF($B$63=0,"Only Google Cloud has a machine big enough for this model.",IF(B22<C22,"Google Cloud saves about $"&TEXT(C22-B22,"#,##0")&" per month ("&TEXT(1-B22/C22,"0.0%")&" less)",IF(C22<B22,"Microsoft Azure saves about $"&TEXT(B22-C22,"#,##0")&" per month ("&TEXT(1-C22/B22,"0.0%")&" less)","The two are within a dollar of each other"))))) -> Microsoft Azure saves about $821 per month (6.3% less)
A27: Reading this fairly: a cheaper hourly rate is not the whole story. Azure sells single H100 and single A100 80GB machines, so small jobs need not rent an eight-GPU node. Google Cloud is usually cheaper per GPU-hour at the top end and its L4 machines are the best value for everyday inference. Availability, your existing contracts and which cloud your data already sits in often matter more than list price.
A31: PAY PER TOKEN INSTEAD - cheapest hosted model on each cloud
A32: Cheapest hosted model at your traffic | B32: =IFERROR(INDEX(Rates!$A$114:$A$134,MATCH(MIN(Rates!$J$114:$J$134),Rates!$J$114:$J$134,0)),"-") -> Gemini 2.5 Flash-Lite | C32: =IFERROR(INDEX(Rates!$A$114:$A$134,MATCH(MIN(Rates!$K$114:$K$134),Rates!$K$114:$K$134,0)),"-") -> GPT-5.6 Luna
A33: Token charges per month | B33: =MIN(Rates!$J$114:$J$134) -> 120 | C33: =MIN(Rates!$K$114:$K$134) -> 320
A34: Support and labour | B34: =Calculator!$B$69 -> 2320 | C34: =Calculator!$B$69 -> 2320 | D34: Running an API integration needs far fewer engineer hours than running machines
A35: TOTAL PER MONTH - pay per token | B35: =B33+B34 -> 2440 | C35: =C33+C34 -> 2640
A36: Self-hosting total per month | B36: =B22 -> 13083.169 | C36: =C22 -> 12261.758
A37: Cheaper approach on this cloud | B37: =IF(B35<B22,"Pay per token","Self-host") -> Pay per token | C37: =IF(C35<C22,"Pay per token","Self-host") -> Pay per token
A39: Cheapest of all four options | B39: =IF(Inference!$B$7<=0,"Enter your expected traffic on the Inference tab to compare against pay-per-token pricing.","Cheapest overall: "&IF(MIN($B$22,$C$22,$B$35,$C$35)=$B$35,"pay per token on Google Cloud using "&$B$32,IF(MIN($B$22,$C$22,$B$35,$C$35)=$C$35,"pay per token on Azure using "&$C$32,IF(MIN($B$22,$C$22,$B$35,$C$35)=$B$22,"self-hosting on Google Cloud on "&$B$5,"self-hosting on Azure on "&$C$5)))&" at about $"&TEXT(MIN($B$22,$C$22,$B$35,$C$35),"#,##0")&" per month, versus $"&TEXT(MAX($B$22,$C$22,$B$35,$C$35),"#,##0")&" for the most expensive of the four.") -> Cheapest overall: pay per token on Google Cloud using Gemini 2.5 Flash-Lite at about $2,440 per month, versus $13,083 for the most expensive of the four.
A42: Why pay-per-token usually wins at low volume and loses at high volume: a rented GPU costs the same whether it is busy or idle, so light traffic pays for mostly-idle hardware. A hosted model charges only for tokens used. Once traffic is heavy enough to keep your own machines busy, the per-token margin you are paying someone else starts to exceed the cost of the hardware. The crossover is usually further out than people expect - change the requests figure on the Inference tab to find yours.
A60: Engine - Google Cloud row | B60: =IFERROR(MATCH(MIN(GPU_Price_List!$X$5:$X$35),GPU_Price_List!$X$5:$X$35,0),0) -> 11
A61: Engine - Azure row | B61: =IFERROR(MATCH(MIN(GPU_Price_List!$Y$5:$Y$35),GPU_Price_List!$Y$5:$Y$35,0),0) -> 24
A62: Engine - GCP found? (1 = yes) | B62: =IF(MIN(GPU_Price_List!$X$5:$X$35)>=1000000000,0,1) -> 1
A63: Engine - Azure found? (1 = yes) | B63: =IF(MIN(GPU_Price_List!$Y$5:$Y$35)>=1000000000,0,1) -> 1
A64: Engine - GCP region uplift | B64: =INDEX(Rates!$B$21:$B$24,MATCH(Calculator!$B$14,Rates!$A$21:$A$24,0)) -> 1
A65: Engine - Azure region uplift | B65: =INDEX(Rates!$C$21:$C$24,MATCH(Calculator!$B$14,Rates!$A$21:$A$24,0)) -> 1

Sheet GPU_Price_List
A1: GPU Machine Price List - Google Cloud and Microsoft Azure, cheapest GPU first
A2: Sorted lowest tier (NVIDIA T4) to highest tier (NVIDIA B200). US-region list prices, August 2026. Columns T onward are used by the Calculator - please leave them alone.
T3: CALCULATOR ENGINE - these six columns react to the Calculator tab. Do not edit. | Z3: THROUGHPUT ENGINE - driven by the Inference tab. Do not edit.
A4: Tier | B4: Tier name | C4: Cloud | D4: GPU model | E4: GPU memory each (GB) | F4: GPUs per machine | G4: Total GPU memory (GB) | H4: Machine / VM size | I4: vCPU | J4: RAM (GB) | K4: On-demand $/hour | L4: Spot $/hour | M4: Spot rate source | N4: 1-Year commit $/hour | O4: On-demand $/month | P4: Good for | Q4: Price confidence | R4: Source | S4: Menu label | T4: Selected rate $/hour | U4: Cloud matches filter? | V4: Enough GPU memory? | W4: Rank - either cloud | X4: Rank - Google Cloud | Y4: Rank - Azure | Z4: GPU bandwidth each (GB/s) | AA4: Total bandwidth (GB/s) | AB4: Output tokens/sec per machine | AC4: Machines needed for the load | AD4: Cost to meet the load $/hour
A5: 1 | B5: T4 16 GB - entry level | C5: Microsoft Azure | D5: NVIDIA T4 | E5: 16 | F5: 1 | G5: =E5*F5 -> 16 | H5: Standard_NC4as_T4_v3 | I5: 4 | J5: 28 | K5: 0.526 | L5: 0.15254 | M5: Published spot rate | N5: =K5*IF(C5=Rates!$A$45,Rates!$B$29,Rates!$C$29) -> 0.3419 | O5: =K5*Rates!$B$30 -> 383.98 | P5: Small models, demos, dev boxes | Q5: Published list price | R5: Azure East US Linux pay-as-you-go (Vantage/CloudPrice) | S5: =C5&" | "&H5 -> Microsoft Azure | Standard_NC4as_T4_v3 | T5: =IF(Calculator!$D$16=Rates!$C$46,L5,IF(Calculator!$D$16=Rates!$C$47,N5,K5)) -> 0.526 | U5: =IF(OR(Calculator!$B$13=Rates!$A$47,Calculator!$B$13=C5),1,0) -> 1 | V5: =IF(G5>=Calculator!$B$10,1,0) -> 0 | W5: =IF(AND(U5=1,V5=1),AD5,1000000000) -> 1000000000 | X5: =IF(AND(C5=Rates!$A$45,V5=1),AD5,1000000000) -> 1000000000 | Y5: =IF(AND(C5=Rates!$A$46,V5=1),AD5,1000000000) -> 1000000000 | Z5: 320 | AA5: =Z5*F5 -> 320 | AB5: =IFERROR(AA5/Calculator!$B$129*Rates!$B$108*Rates!$B$109,0) -> 51.2 | AC5: =IF(Inference!$B$16<=0,1,IF(AB5<=0,1000000000,MAX(1,ROUNDUP(Inference!$B$16/AB5,0)))) -> 6 | AD5: =T5*AC5+AC5/1000000 -> 3.156006
A6: 1 | B6: T4 16 GB - entry level | C6: Google Cloud | D6: NVIDIA T4 | E6: 16 | F6: 1 | G6: =E6*F6 -> 16 | H6: n1-standard-4 + 1x T4 | I6: 4 | J6: 15 | K6: 0.54 | L6: =K6*IF(C6=Rates!$A$45,Rates!$B$28,Rates!$C$28) -> 0.1782 | M6: Estimated (cloud default factor) | N6: =K6*IF(C6=Rates!$A$45,Rates!$B$29,Rates!$C$29) -> 0.378 | O6: =K6*Rates!$B$30 -> 394.2 | P6: Small models, demos, dev boxes | Q6: Published list price | R6: GCP: n1-standard-4 $0.1900/hr + T4 $0.35/GPU/hr, us-central1 | S6: =C6&" | "&H6 -> Google Cloud | n1-standard-4 + 1x T4 | T6: =IF(Calculator!$D$16=Rates!$C$46,L6,IF(Calculator!$D$16=Rates!$C$47,N6,K6)) -> 0.54 | U6: =IF(OR(Calculator!$B$13=Rates!$A$47,Calculator!$B$13=C6),1,0) -> 1 | V6: =IF(G6>=Calculator!$B$10,1,0) -> 0 | W6: =IF(AND(U6=1,V6=1),AD6,1000000000) -> 1000000000 | X6: =IF(AND(C6=Rates!$A$45,V6=1),AD6,1000000000) -> 1000000000 | Y6: =IF(AND(C6=Rates!$A$46,V6=1),AD6,1000000000) -> 1000000000 | Z6: 320 | AA6: =Z6*F6 -> 320 | AB6: =IFERROR(AA6/Calculator!$B$129*Rates!$B$108*Rates!$B$109,0) -> 51.2 | AC6: =IF(Inference!$B$16<=0,1,IF(AB6<=0,1000000000,MAX(1,ROUNDUP(Inference!$B$16/AB6,0)))) -> 6 | AD6: =T6*AC6+AC6/1000000 -> 3.240006
A7: 1 | B7: T4 16 GB - entry level | C7: Google Cloud | D7: NVIDIA T4 | E7: 16 | F7: 1 | G7: =E7*F7 -> 16 | H7: n1-standard-8 + 1x T4 | I7: 8 | J7: 30 | K7: 0.73 | L7: =K7*IF(C7=Rates!$A$45,Rates!$B$28,Rates!$C$28) -> 0.2409 | M7: Estimated (cloud default factor) | N7: =K7*IF(C7=Rates!$A$45,Rates!$B$29,Rates!$C$29) -> 0.511 | O7: =K7*Rates!$B$30 -> 532.9 | P7: Small models with more CPU-side work | Q7: Published list price | R7: GCP: n1-standard-8 $0.3800/hr + T4 $0.35/GPU/hr, us-central1 | S7: =C7&" | "&H7 -> Google Cloud | n1-standard-8 + 1x T4 | T7: =IF(Calculator!$D$16=Rates!$C$46,L7,IF(Calculator!$D$16=Rates!$C$47,N7,K7)) -> 0.73 | U7: =IF(OR(Calculator!$B$13=Rates!$A$47,Calculator!$B$13=C7),1,0) -> 1 | V7: =IF(G7>=Calculator!$B$10,1,0) -> 0 | W7: =IF(AND(U7=1,V7=1),AD7,1000000000) -> 1000000000 | X7: =IF(AND(C7=Rates!$A$45,V7=1),AD7,1000000000) -> 1000000000 | Y7: =IF(AND(C7=Rates!$A$46,V7=1),AD7,1000000000) -> 1000000000 | Z7: 320 | AA7: =Z7*F7 -> 320 | AB7: =IFERROR(AA7/Calculator!$B$129*Rates!$B$108*Rates!$B$109,0) -> 51.2 | AC7: =IF(Inference!$B$16<=0,1,IF(AB7<=0,1000000000,MAX(1,ROUNDUP(Inference!$B$16/AB7,0)))) -> 6 | AD7: =T7*AC7+AC7/1000000 -> 4.380006
A8: 1 | B8: T4 16 GB - entry level | C8: Microsoft Azure | D8: NVIDIA T4 | E8: 16 | F8: 1 | G8: =E8*F8 -> 16 | H8: Standard_NC8as_T4_v3 | I8: 8 | J8: 56 | K8: 0.752 | L8: 0.256958 | M8: Published spot rate | N8: =K8*IF(C8=Rates!$A$45,Rates!$B$29,Rates!$C$29) -> 0.4888 | O8: =K8*Rates!$B$30 -> 548.96 | P8: Small models with more CPU-side work | Q8: Published list price | R8: Azure East US Linux pay-as-you-go (Vantage/CloudPrice) | S8: =C8&" | "&H8 -> Microsoft Azure | Standard_NC8as_T4_v3 | T8: =IF(Calculator!$D$16=Rates!$C$46,L8,IF(Calculator!$D$16=Rates!$C$47,N8,K8)) -> 0.752 | U8: =IF(OR(Calculator!$B$13=Rates!$A$47,Calculator!$B$13=C8),1,0) -> 1 | V8: =IF(G8>=Calculator!$B$10,1,0) -> 0 | W8: =IF(AND(U8=1,V8=1),AD8,1000000000) -> 1000000000 | X8: =IF(AND(C8=Rates!$A$45,V8=1),AD8,1000000000) -> 1000000000 | Y8: =IF(AND(C8=Rates!$A$46,V8=1),AD8,1000000000) -> 1000000000 | Z8: 320 | AA8: =Z8*F8 -> 320 | AB8: =IFERROR(AA8/Calculator!$B$129*Rates!$B$108*Rates!$B$109,0) -> 51.2 | AC8: =IF(Inference!$B$16<=0,1,IF(AB8<=0,1000000000,MAX(1,ROUNDUP(Inference!$B$16/AB8,0)))) -> 6 | AD8: =T8*AC8+AC8/1000000 -> 4.512006
A9: 1 | B9: T4 16 GB - entry level | C9: Google Cloud | D9: NVIDIA T4 | E9: 16 | F9: 2 | G9: =E9*F9 -> 32 | H9: n1-standard-8 + 2x T4 | I9: 8 | J9: 30 | K9: 1.08 | L9: =K9*IF(C9=Rates!$A$45,Rates!$B$28,Rates!$C$28) -> 0.3564 | M9: Estimated (cloud default factor) | N9: =K9*IF(C9=Rates!$A$45,Rates!$B$29,Rates!$C$29) -> 0.756 | O9: =K9*Rates!$B$30 -> 788.4 | P9: Mid-size model split over 2 cheap GPUs | Q9: Published list price | R9: GCP: n1-standard-8 $0.3800/hr + 2x T4 @ $0.35/GPU/hr, us-central1 | S9: =C9&" | "&H9 -> Google Cloud | n1-standard-8 + 2x T4 | T9: =IF(Calculator!$D$16=Rates!$C$46,L9,IF(Calculator!$D$16=Rates!$C$47,N9,K9)) -> 1.08 | U9: =IF(OR(Calculator!$B$13=Rates!$A$47,Calculator!$B$13=C9),1,0) -> 1 | V9: =IF(G9>=Calculator!$B$10,1,0) -> 0 | W9: =IF(AND(U9=1,V9=1),AD9,1000000000) -> 1000000000 | X9: =IF(AND(C9=Rates!$A$45,V9=1),AD9,1000000000) -> 1000000000 | Y9: =IF(AND(C9=Rates!$A$46,V9=1),AD9,1000000000) -> 1000000000 | Z9: 320 | AA9: =Z9*F9 -> 640 | AB9: =IFERROR(AA9/Calculator!$B$129*Rates!$B$108*Rates!$B$109,0) -> 102.4 | AC9: =IF(Inference!$B$16<=0,1,IF(AB9<=0,1000000000,MAX(1,ROUNDUP(Inference!$B$16/AB9,0)))) -> 3 | AD9: =T9*AC9+AC9/1000000 -> 3.240003
A10: 2 | B10: L4 / A10 24 GB - inference workhorse | C10: Google Cloud | D10: NVIDIA L4 | E10: 24 | F10: 1 | G10: =E10*F10 -> 24 | H10: g2-standard-4 | I10: 4 | J10: 16 | K10: 0.7068 | L10: 0.2818 | M10: Published spot rate | N10: =K10*IF(C10=Rates!$A$45,Rates!$B$29,Rates!$C$29) -> 0.49476 | O10: =K10*Rates!$B$30 -> 515.964 | P10: Best value for everyday inference | Q10: Published list price | R10: GCP accelerator-optimized pricing, us-central1 | S10: =C10&" | "&H10 -> Google Cloud | g2-standard-4 | T10: =IF(Calculator!$D$16=Rates!$C$46,L10,IF(Calculator!$D$16=Rates!$C$47,N10,K10)) -> 0.7068 | U10: =IF(OR(Calculator!$B$13=Rates!$A$47,Calculator!$B$13=C10),1,0) -> 1 | V10: =IF(G10>=Calculator!$B$10,1,0) -> 0 | W10: =IF(AND(U10=1,V10=1),AD10,1000000000) -> 1000000000 | X10: =IF(AND(C10=Rates!$A$45,V10=1),AD10,1000000000) -> 1000000000 | Y10: =IF(AND(C10=Rates!$A$46,V10=1),AD10,1000000000) -> 1000000000 | Z10: 300 | AA10: =Z10*F10 -> 300 | AB10: =IFERROR(AA10/Calculator!$B$129*Rates!$B$108*Rates!$B$109,0) -> 48 | AC10: =IF(Inference!$B$16<=0,1,IF(AB10<=0,1000000000,MAX(1,ROUNDUP(Inference!$B$16/AB10,0)))) -> 6 | AD10: =T10*AC10+AC10/1000000 -> 4.240806
A11: 2 | B11: L4 / A10 24 GB - inference workhorse | C11: Google Cloud | D11: NVIDIA L4 | E11: 24 | F11: 1 | G11: =E11*F11 -> 24 | H11: g2-standard-8 | I11: 8 | J11: 32 | K11: 0.8536 | L11: 0.3406 | M11: Published spot rate | N11: =K11*IF(C11=Rates!$A$45,Rates!$B$29,Rates!$C$29) -> 0.59752 | O11: =K11*Rates!$B$30 -> 623.128 | P11: Everyday inference, more RAM | Q11: Published list price | R11: GCP accelerator-optimized pricing, us-central1 | S11: =C11&" | "&H11 -> Google Cloud | g2-standard-8 | T11: =IF(Calculator!$D$16=Rates!$C$46,L11,IF(Calculator!$D$16=Rates!$C$47,N11,K11)) -> 0.8536 | U11: =IF(OR(Calculator!$B$13=Rates!$A$47,Calculator!$B$13=C11),1,0) -> 1 | V11: =IF(G11>=Calculator!$B$10,1,0) -> 0 | W11: =IF(AND(U11=1,V11=1),AD11,1000000000) -> 1000000000 | X11: =IF(AND(C11=Rates!$A$45,V11=1),AD11,1000000000) -> 1000000000 | Y11: =IF(AND(C11=Rates!$A$46,V11=1),AD11,1000000000) -> 1000000000 | Z11: 300 | AA11: =Z11*F11 -> 300 | AB11: =IFERROR(AA11/Calculator!$B$129*Rates!$B$108*Rates!$B$109,0) -> 48 | AC11: =IF(Inference!$B$16<=0,1,IF(AB11<=0,1000000000,MAX(1,ROUNDUP(Inference!$B$16/AB11,0)))) -> 6 | AD11: =T11*AC11+AC11/1000000 -> 5.121606
A12: 2 | B12: L4 / A10 24 GB - inference workhorse | C12: Google Cloud | D12: NVIDIA L4 | E12: 24 | F12: 2 | G12: =E12*F12 -> 48 | H12: g2-standard-24 | I12: 24 | J12: 96 | K12: 2.0008 | L12: 0.7986 | M12: Published spot rate | N12: =K12*IF(C12=Rates!$A$45,Rates!$B$29,Rates!$C$29) -> 1.40056 | O12: =K12*Rates!$B$30 -> 1460.584 | P12: Two GPUs for larger models | Q12: Published list price | R12: GCP accelerator-optimized pricing, us-central1 | S12: =C12&" | "&H12 -> Google Cloud | g2-standard-24 | T12: =IF(Calculator!$D$16=Rates!$C$46,L12,IF(Calculator!$D$16=Rates!$C$47,N12,K12)) -> 2.0008 | U12: =IF(OR(Calculator!$B$13=Rates!$A$47,Calculator!$B$13=C12),1,0) -> 1 | V12: =IF(G12>=Calculator!$B$10,1,0) -> 0 | W12: =IF(AND(U12=1,V12=1),AD12,1000000000) -> 1000000000 | X12: =IF(AND(C12=Rates!$A$45,V12=1),AD12,1000000000) -> 1000000000 | Y12: =IF(AND(C12=Rates!$A$46,V12=1),AD12,1000000000) -> 1000000000 | Z12: 300 | AA12: =Z12*F12 -> 600 | AB12: =IFERROR(AA12/Calculator!$B$129*Rates!$B$108*Rates!$B$109,0) -> 96 | AC12: =IF(Inference!$B$16<=0,1,IF(AB12<=0,1000000000,MAX(1,ROUNDUP(Inference!$B$16/AB12,0)))) -> 3 | AD12: =T12*AC12+AC12/1000000 -> 6.002403
A13: 2 | B13: L4 / A10 24 GB - inference workhorse | C13: Microsoft Azure | D13: NVIDIA A10 | E13: 24 | F13: 1 | G13: =E13*F13 -> 24 | H13: Standard_NV36ads_A10_v5 | I13: 36 | J13: 440 | K13: 3.2 | L13: 0.59136 | M13: Published spot rate | N13: =K13*IF(C13=Rates!$A$45,Rates!$B$29,Rates!$C$29) -> 2.08 | O13: =K13*Rates!$B$30 -> 2336 | P13: Inference plus heavy CPU pre/post-processing | Q13: Published list price | R13: Azure East US Linux pay-as-you-go (Vantage) | S13: =C13&" | "&H13 -> Microsoft Azure | Standard_NV36ads_A10_v5 | T13: =IF(Calculator!$D$16=Rates!$C$46,L13,IF(Calculator!$D$16=Rates!$C$47,N13,K13)) -> 3.2 | U13: =IF(OR(Calculator!$B$13=Rates!$A$47,Calculator!$B$13=C13),1,0) -> 1 | V13: =IF(G13>=Calculator!$B$10,1,0) -> 0 | W13: =IF(AND(U13=1,V13=1),AD13,1000000000) -> 1000000000 | X13: =IF(AND(C13=Rates!$A$45,V13=1),AD13,1000000000) -> 1000000000 | Y13: =IF(AND(C13=Rates!$A$46,V13=1),AD13,1000000000) -> 1000000000 | Z13: 600 | AA13: =Z13*F13 -> 600 | AB13: =IFERROR(AA13/Calculator!$B$129*Rates!$B$108*Rates!$B$109,0) -> 96 | AC13: =IF(Inference!$B$16<=0,1,IF(AB13<=0,1000000000,MAX(1,ROUNDUP(Inference!$B$16/AB13,0)))) -> 3 | AD13: =T13*AC13+AC13/1000000 -> 9.600003
A14: 2 | B14: L4 / A10 24 GB - inference workhorse | C14: Google Cloud | D14: NVIDIA L4 | E14: 24 | F14: 4 | G14: =E14*F14 -> 96 | H14: g2-standard-48 | I14: 48 | J14: 192 | K14: 4.0017 | L14: 1.5972 | M14: Published spot rate | N14: =K14*IF(C14=Rates!$A$45,Rates!$B$29,Rates!$C$29) -> 2.80119 | O14: =K14*Rates!$B$30 -> 2921.241 | P14: Four GPUs, high throughput serving | Q14: Published list price | R14: GCP accelerator-optimized pricing, us-central1 | S14: =C14&" | "&H14 -> Google Cloud | g2-standard-48 | T14: =IF(Calculator!$D$16=Rates!$C$46,L14,IF(Calculator!$D$16=Rates!$C$47,N14,K14)) -> 4.0017 | U14: =IF(OR(Calculator!$B$13=Rates!$A$47,Calculator!$B$13=C14),1,0) -> 1 | V14: =IF(G14>=Calculator!$B$10,1,0) -> 1 | W14: =IF(AND(U14=1,V14=1),AD14,1000000000) -> 8.003402 | X14: =IF(AND(C14=Rates!$A$45,V14=1),AD14,1000000000) -> 8.003402 | Y14: =IF(AND(C14=Rates!$A$46,V14=1),AD14,1000000000) -> 1000000000 | Z14: 300 | AA14: =Z14*F14 -> 1200 | AB14: =IFERROR(AA14/Calculator!$B$129*Rates!$B$108*Rates!$B$109,0) -> 192 | AC14: =IF(Inference!$B$16<=0,1,IF(AB14<=0,1000000000,MAX(1,ROUNDUP(Inference!$B$16/AB14,0)))) -> 2 | AD14: =T14*AC14+AC14/1000000 -> 8.003402
A15: 2 | B15: L4 / A10 24 GB - inference workhorse | C15: Google Cloud | D15: NVIDIA L4 | E15: 24 | F15: 8 | G15: =E15*F15 -> 192 | H15: g2-standard-96 | I15: 96 | J15: 384 | K15: 8.0033 | L15: 3.1945 | M15: Published spot rate | N15: =K15*IF(C15=Rates!$A$45,Rates!$B$29,Rates!$C$29) -> 5.60231 | O15: =K15*Rates!$B$30 -> 5842.409 | P15: Eight GPUs, high throughput serving | Q15: Published list price | R15: GCP accelerator-optimized pricing, us-central1 | S15: =C15&" | "&H15 -> Google Cloud | g2-standard-96 | T15: =IF(Calculator!$D$16=Rates!$C$46,L15,IF(Calculator!$D$16=Rates!$C$47,N15,K15)) -> 8.0033 | U15: =IF(OR(Calculator!$B$13=Rates!$A$47,Calculator!$B$13=C15),1,0) -> 1 | V15: =IF(G15>=Calculator!$B$10,1,0) -> 1 | W15: =IF(AND(U15=1,V15=1),AD15,1000000000) -> 8.003301 | X15: =IF(AND(C15=Rates!$A$45,V15=1),AD15,1000000000) -> 8.003301 | Y15: =IF(AND(C15=Rates!$A$46,V15=1),AD15,1000000000) -> 1000000000 | Z15: 300 | AA15: =Z15*F15 -> 2400 | AB15: =IFERROR(AA15/Calculator!$B$129*Rates!$B$108*Rates!$B$109,0) -> 384 | AC15: =IF(Inference!$B$16<=0,1,IF(AB15<=0,1000000000,MAX(1,ROUNDUP(Inference!$B$16/AB15,0)))) -> 1 | AD15: =T15*AC15+AC15/1000000 -> 8.003301
A16: 3 | B16: A100 40 GB - training and large inference | C16: Google Cloud | D16: NVIDIA A100 40GB | E16: 40 | F16: 1 | G16: =E16*F16 -> 40 | H16: a2-highgpu-1g | I16: 12 | J16: 85 | K16: 3.6734 | L16: 1.443 | M16: Published spot rate | N16: =K16*IF(C16=Rates!$A$45,Rates!$B$29,Rates!$C$29) -> 2.57138 | O16: =K16*Rates!$B$30 -> 2681.582 | P16: Entry point for single-GPU A100 work | Q16: Published list price | R16: GCP accelerator-optimized pricing, us-central1 | S16: =C16&" | "&H16 -> Google Cloud | a2-highgpu-1g | T16: =IF(Calculator!$D$16=Rates!$C$46,L16,IF(Calculator!$D$16=Rates!$C$47,N16,K16)) -> 3.6734 | U16: =IF(OR(Calculator!$B$13=Rates!$A$47,Calculator!$B$13=C16),1,0) -> 1 | V16: =IF(G16>=Calculator!$B$10,1,0) -> 0 | W16: =IF(AND(U16=1,V16=1),AD16,1000000000) -> 1000000000 | X16: =IF(AND(C16=Rates!$A$45,V16=1),AD16,1000000000) -> 1000000000 | Y16: =IF(AND(C16=Rates!$A$46,V16=1),AD16,1000000000) -> 1000000000 | Z16: 1555 | AA16: =Z16*F16 -> 1555 | AB16: =IFERROR(AA16/Calculator!$B$129*Rates!$B$108*Rates!$B$109,0) -> 248.8 | AC16: =IF(Inference!$B$16<=0,1,IF(AB16<=0,1000000000,MAX(1,ROUNDUP(Inference!$B$16/AB16,0)))) -> 2 | AD16: =T16*AC16+AC16/1000000 -> 7.346802
A17: 3 | B17: A100 40 GB - training and large inference | C17: Google Cloud | D17: NVIDIA A100 40GB | E17: 40 | F17: 2 | G17: =E17*F17 -> 80 | H17: a2-highgpu-2g | I17: 24 | J17: 170 | K17: 7.3468 | L17: 2.8859 | M17: Published spot rate | N17: =K17*IF(C17=Rates!$A$45,Rates!$B$29,Rates!$C$29) -> 5.14276 | O17: =K17*Rates!$B$30 -> 5363.164 | P17: Fine-tuning mid-size models | Q17: Published list price | R17: GCP accelerator-optimized pricing, us-central1 | S17: =C17&" | "&H17 -> Google Cloud | a2-highgpu-2g | T17: =IF(Calculator!$D$16=Rates!$C$46,L17,IF(Calculator!$D$16=Rates!$C$47,N17,K17)) -> 7.3468 | U17: =IF(OR(Calculator!$B$13=Rates!$A$47,Calculator!$B$13=C17),1,0) -> 1 | V17: =IF(G17>=Calculator!$B$10,1,0) -> 0 | W17: =IF(AND(U17=1,V17=1),AD17,1000000000) -> 1000000000 | X17: =IF(AND(C17=Rates!$A$45,V17=1),AD17,1000000000) -> 1000000000 | Y17: =IF(AND(C17=Rates!$A$46,V17=1),AD17,1000000000) -> 1000000000 | Z17: 1555 | AA17: =Z17*F17 -> 3110 | AB17: =IFERROR(AA17/Calculator!$B$129*Rates!$B$108*Rates!$B$109,0) -> 497.6 | AC17: =IF(Inference!$B$16<=0,1,IF(AB17<=0,1000000000,MAX(1,ROUNDUP(Inference!$B$16/AB17,0)))) -> 1 | AD17: =T17*AC17+AC17/1000000 -> 7.346801
A18: 3 | B18: A100 40 GB - training and large inference | C18: Google Cloud | D18: NVIDIA A100 40GB | E18: 40 | F18: 4 | G18: =E18*F18 -> 160 | H18: a2-highgpu-4g | I18: 48 | J18: 340 | K18: 14.6935 | L18: 5.7718 | M18: Published spot rate | N18: =K18*IF(C18=Rates!$A$45,Rates!$B$29,Rates!$C$29) -> 10.28545 | O18: =K18*Rates!$B$30 -> 10726.255 | P18: Fine-tuning and multi-GPU serving | Q18: Published list price | R18: GCP accelerator-optimized pricing, us-central1 | S18: =C18&" | "&H18 -> Google Cloud | a2-highgpu-4g | T18: =IF(Calculator!$D$16=Rates!$C$46,L18,IF(Calculator!$D$16=Rates!$C$47,N18,K18)) -> 14.6935 | U18: =IF(OR(Calculator!$B$13=Rates!$A$47,Calculator!$B$13=C18),1,0) -> 1 | V18: =IF(G18>=Calculator!$B$10,1,0) -> 1 | W18: =IF(AND(U18=1,V18=1),AD18,1000000000) -> 14.693501 | X18: =IF(AND(C18=Rates!$A$45,V18=1),AD18,1000000000) -> 14.693501 | Y18: =IF(AND(C18=Rates!$A$46,V18=1),AD18,1000000000) -> 1000000000 | Z18: 1555 | AA18: =Z18*F18 -> 6220 | AB18: =IFERROR(AA18/Calculator!$B$129*Rates!$B$108*Rates!$B$109,0) -> 995.2 | AC18: =IF(Inference!$B$16<=0,1,IF(AB18<=0,1000000000,MAX(1,ROUNDUP(Inference!$B$16/AB18,0)))) -> 1 | AD18: =T18*AC18+AC18/1000000 -> 14.693501
A19: 3 | B19: A100 40 GB - training and large inference | C19: Google Cloud | D19: NVIDIA A100 40GB | E19: 40 | F19: 8 | G19: =E19*F19 -> 320 | H19: a2-highgpu-8g | I19: 96 | J19: 680 | K19: 29.3871 | L19: 11.5436 | M19: Published spot rate | N19: =K19*IF(C19=Rates!$A$45,Rates!$B$29,Rates!$C$29) -> 20.57097 | O19: =K19*Rates!$B$30 -> 21452.583 | P19: Lowest-cost 8x A100 node | Q19: Published list price | R19: GCP accelerator-optimized pricing, us-central1 | S19: =C19&" | "&H19 -> Google Cloud | a2-highgpu-8g | T19: =IF(Calculator!$D$16=Rates!$C$46,L19,IF(Calculator!$D$16=Rates!$C$47,N19,K19)) -> 29.3871 | U19: =IF(OR(Calculator!$B$13=Rates!$A$47,Calculator!$B$13=C19),1,0) -> 1 | V19: =IF(G19>=Calculator!$B$10,1,0) -> 1 | W19: =IF(AND(U19=1,V19=1),AD19,1000000000) -> 29.387101 | X19: =IF(AND(C19=Rates!$A$45,V19=1),AD19,1000000000) -> 29.387101 | Y19: =IF(AND(C19=Rates!$A$46,V19=1),AD19,1000000000) -> 1000000000 | Z19: 1555 | AA19: =Z19*F19 -> 12440 | AB19: =IFERROR(AA19/Calculator!$B$129*Rates!$B$108*Rates!$B$109,0) -> 1990.4 | AC19: =IF(Inference!$B$16<=0,1,IF(AB19<=0,1000000000,MAX(1,ROUNDUP(Inference!$B$16/AB19,0)))) -> 1 | AD19: =T19*AC19+AC19/1000000 -> 29.387101
A20: 3 | B20: A100 40 GB - training and large inference | C20: Google Cloud | D20: NVIDIA A100 40GB | E20: 40 | F20: 16 | G20: =E20*F20 -> 640 | H20: a2-megagpu-16g | I20: 96 | J20: 1360 | K20: 55.7395 | L20: 21.8738 | M20: Published spot rate | N20: =K20*IF(C20=Rates!$A$45,Rates!$B$29,Rates!$C$29) -> 39.01765 | O20: =K20*Rates!$B$30 -> 40689.835 | P20: 16 GPUs in one machine | Q20: Published list price | R20: GCP accelerator-optimized pricing, us-central1 | S20: =C20&" | "&H20 -> Google Cloud | a2-megagpu-16g | T20: =IF(Calculator!$D$16=Rates!$C$46,L20,IF(Calculator!$D$16=Rates!$C$47,N20,K20)) -> 55.7395 | U20: =IF(OR(Calculator!$B$13=Rates!$A$47,Calculator!$B$13=C20),1,0) -> 1 | V20: =IF(G20>=Calculator!$B$10,1,0) -> 1 | W20: =IF(AND(U20=1,V20=1),AD20,1000000000) -> 55.739501 | X20: =IF(AND(C20=Rates!$A$45,V20=1),AD20,1000000000) -> 55.739501 | Y20: =IF(AND(C20=Rates!$A$46,V20=1),AD20,1000000000) -> 1000000000 | Z20: 1555 | AA20: =Z20*F20 -> 24880 | AB20: =IFERROR(AA20/Calculator!$B$129*Rates!$B$108*Rates!$B$109,0) -> 3980.8 | AC20: =IF(Inference!$B$16<=0,1,IF(AB20<=0,1000000000,MAX(1,ROUNDUP(Inference!$B$16/AB20,0)))) -> 1 | AD20: =T20*AC20+AC20/1000000 -> 55.739501
A21: 4 | B21: A100 80 GB - larger models per GPU | C21: Microsoft Azure | D21: NVIDIA A100 80GB | E21: 80 | F21: 1 | G21: =E21*F21 -> 80 | H21: Standard_NC24ads_A100_v4 | I21: 24 | J21: 220 | K21: 3.673 | L21: 0.67877 | M21: Published spot rate | N21: =K21*IF(C21=Rates!$A$45,Rates!$B$29,Rates!$C$29) -> 2.38745 | O21: =K21*Rates!$B$30 -> 2681.29 | P21: Cheapest single 80 GB GPU on Azure | Q21: Published list price | R21: Azure East US Linux pay-as-you-go (Vantage) | S21: =C21&" | "&H21 -> Microsoft Azure | Standard_NC24ads_A100_v4 | T21: =IF(Calculator!$D$16=Rates!$C$46,L21,IF(Calculator!$D$16=Rates!$C$47,N21,K21)) -> 3.673 | U21: =IF(OR(Calculator!$B$13=Rates!$A$47,Calculator!$B$13=C21),1,0) -> 1 | V21: =IF(G21>=Calculator!$B$10,1,0) -> 0 | W21: =IF(AND(U21=1,V21=1),AD21,1000000000) -> 1000000000 | X21: =IF(AND(C21=Rates!$A$45,V21=1),AD21,1000000000) -> 1000000000 | Y21: =IF(AND(C21=Rates!$A$46,V21=1),AD21,1000000000) -> 1000000000 | Z21: 2039 | AA21: =Z21*F21 -> 2039 | AB21: =IFERROR(AA21/Calculator!$B$129*Rates!$B$108*Rates!$B$109,0) -> 326.24 | AC21: =IF(Inference!$B$16<=0,1,IF(AB21<=0,1000000000,MAX(1,ROUNDUP(Inference!$B$16/AB21,0)))) -> 1 | AD21: =T21*AC21+AC21/1000000 -> 3.673001
A22: 4 | B22: A100 80 GB - larger models per GPU | C22: Google Cloud | D22: NVIDIA A100 80GB | E22: 80 | F22: 1 | G22: =E22*F22 -> 80 | H22: a2-ultragpu-1g | I22: 12 | J22: 170 | K22: 5.0688 | L22: 2.025 | M22: Published spot rate | N22: =K22*IF(C22=Rates!$A$45,Rates!$B$29,Rates!$C$29) -> 3.54816 | O22: =K22*Rates!$B$30 -> 3700.224 | P22: Single 80 GB GPU on GCP | Q22: Published list price | R22: GCP accelerator-optimized pricing, us-central1 | S22: =C22&" | "&H22 -> Google Cloud | a2-ultragpu-1g | T22: =IF(Calculator!$D$16=Rates!$C$46,L22,IF(Calculator!$D$16=Rates!$C$47,N22,K22)) -> 5.0688 | U22: =IF(OR(Calculator!$B$13=Rates!$A$47,Calculator!$B$13=C22),1,0) -> 1 | V22: =IF(G22>=Calculator!$B$10,1,0) -> 0 | W22: =IF(AND(U22=1,V22=1),AD22,1000000000) -> 1000000000 | X22: =IF(AND(C22=Rates!$A$45,V22=1),AD22,1000000000) -> 1000000000 | Y22: =IF(AND(C22=Rates!$A$46,V22=1),AD22,1000000000) -> 1000000000 | Z22: 2039 | AA22: =Z22*F22 -> 2039 | AB22: =IFERROR(AA22/Calculator!$B$129*Rates!$B$108*Rates!$B$109,0) -> 326.24 | AC22: =IF(Inference!$B$16<=0,1,IF(AB22<=0,1000000000,MAX(1,ROUNDUP(Inference!$B$16/AB22,0)))) -> 1 | AD22: =T22*AC22+AC22/1000000 -> 5.068801
A23: 4 | B23: A100 80 GB - larger models per GPU | C23: Microsoft Azure | D23: NVIDIA A100 80GB | E23: 80 | F23: 2 | G23: =E23*F23 -> 160 | H23: Standard_NC48ads_A100_v4 | I23: 48 | J23: 440 | K23: 7.346 | L23: =K23*IF(C23=Rates!$A$45,Rates!$B$28,Rates!$C$28) -> 1.39574 | M23: Estimated (cloud default factor) | N23: =K23*IF(C23=Rates!$A$45,Rates!$B$29,Rates!$C$29) -> 4.7749 | O23: =K23*Rates!$B$30 -> 5362.58 | P23: Two 80 GB GPUs | Q23: Scaled from the 1-GPU rate | R23: Scaled 2x from NC24ads A100 v4 published rate - confirm in Azure calculator | S23: =C23&" | "&H23 -> Microsoft Azure | Standard_NC48ads_A100_v4 | T23: =IF(Calculator!$D$16=Rates!$C$46,L23,IF(Calculator!$D$16=Rates!$C$47,N23,K23)) -> 7.346 | U23: =IF(OR(Calculator!$B$13=Rates!$A$47,Calculator!$B$13=C23),1,0) -> 1 | V23: =IF(G23>=Calculator!$B$10,1,0) -> 1 | W23: =IF(AND(U23=1,V23=1),AD23,1000000000) -> 7.346001 | X23: =IF(AND(C23=Rates!$A$45,V23=1),AD23,1000000000) -> 1000000000 | Y23: =IF(AND(C23=Rates!$A$46,V23=1),AD23,1000000000) -> 7.346001 | Z23: 2039 | AA23: =Z23*F23 -> 4078 | AB23: =IFERROR(AA23/Calculator!$B$129*Rates!$B$108*Rates!$B$109,0) -> 652.48 | AC23: =IF(Inference!$B$16<=0,1,IF(AB23<=0,1000000000,MAX(1,ROUNDUP(Inference!$B$16/AB23,0)))) -> 1 | AD23: =T23*AC23+AC23/1000000 -> 7.346001
A24: 4 | B24: A100 80 GB - larger models per GPU | C24: Google Cloud | D24: NVIDIA A100 80GB | E24: 80 | F24: 2 | G24: =E24*F24 -> 160 | H24: a2-ultragpu-2g | I24: 24 | J24: 340 | K24: 10.1376 | L24: 4.05 | M24: Published spot rate | N24: =K24*IF(C24=Rates!$A$45,Rates!$B$29,Rates!$C$29) -> 7.09632 | O24: =K24*Rates!$B$30 -> 7400.448 | P24: Two 80 GB GPUs | Q24: Published list price | R24: GCP accelerator-optimized pricing, us-central1 | S24: =C24&" | "&H24 -> Google Cloud | a2-ultragpu-2g | T24: =IF(Calculator!$D$16=Rates!$C$46,L24,IF(Calculator!$D$16=Rates!$C$47,N24,K24)) -> 10.1376 | U24: =IF(OR(Calculator!$B$13=Rates!$A$47,Calculator!$B$13=C24),1,0) -> 1 | V24: =IF(G24>=Calculator!$B$10,1,0) -> 1 | W24: =IF(AND(U24=1,V24=1),AD24,1000000000) -> 10.137601 | X24: =IF(AND(C24=Rates!$A$45,V24=1),AD24,1000000000) -> 10.137601 | Y24: =IF(AND(C24=Rates!$A$46,V24=1),AD24,1000000000) -> 1000000000 | Z24: 2039 | AA24: =Z24*F24 -> 4078 | AB24: =IFERROR(AA24/Calculator!$B$129*Rates!$B$108*Rates!$B$109,0) -> 652.48 | AC24: =IF(Inference!$B$16<=0,1,IF(AB24<=0,1000000000,MAX(1,ROUNDUP(Inference!$B$16/AB24,0)))) -> 1 | AD24: =T24*AC24+AC24/1000000 -> 10.137601
A25: 4 | B25: A100 80 GB - larger models per GPU | C25: Microsoft Azure | D25: NVIDIA A100 80GB | E25: 80 | F25: 4 | G25: =E25*F25 -> 320 | H25: Standard_NC96ads_A100_v4 | I25: 96 | J25: 880 | K25: 14.692 | L25: =K25*IF(C25=Rates!$A$45,Rates!$B$28,Rates!$C$28) -> 2.79148 | M25: Estimated (cloud default factor) | N25: =K25*IF(C25=Rates!$A$45,Rates!$B$29,Rates!$C$29) -> 9.5498 | O25: =K25*Rates!$B$30 -> 10725.16 | P25: Four 80 GB GPUs | Q25: Scaled from the 1-GPU rate | R25: Scaled 4x from NC24ads A100 v4 published rate - confirm in Azure calculator | S25: =C25&" | "&H25 -> Microsoft Azure | Standard_NC96ads_A100_v4 | T25: =IF(Calculator!$D$16=Rates!$C$46,L25,IF(Calculator!$D$16=Rates!$C$47,N25,K25)) -> 14.692 | U25: =IF(OR(Calculator!$B$13=Rates!$A$47,Calculator!$B$13=C25),1,0) -> 1 | V25: =IF(G25>=Calculator!$B$10,1,0) -> 1 | W25: =IF(AND(U25=1,V25=1),AD25,1000000000) -> 14.692001 | X25: =IF(AND(C25=Rates!$A$45,V25=1),AD25,1000000000) -> 1000000000 | Y25: =IF(AND(C25=Rates!$A$46,V25=1),AD25,1000000000) -> 14.692001 | Z25: 2039 | AA25: =Z25*F25 -> 8156 | AB25: =IFERROR(AA25/Calculator!$B$129*Rates!$B$108*Rates!$B$109,0) -> 1304.96 | AC25: =IF(Inference!$B$16<=0,1,IF(AB25<=0,1000000000,MAX(1,ROUNDUP(Inference!$B$16/AB25,0)))) -> 1 | AD25: =T25*AC25+AC25/1000000 -> 14.692001
A26: 4 | B26: A100 80 GB - larger models per GPU | C26: Google Cloud | D26: NVIDIA A100 80GB | E26: 80 | F26: 4 | G26: =E26*F26 -> 320 | H26: a2-ultragpu-4g | I26: 48 | J26: 680 | K26: 20.2752 | L26: 8.1 | M26: Published spot rate | N26: =K26*IF(C26=Rates!$A$45,Rates!$B$29,Rates!$C$29) -> 14.19264 | O26: =K26*Rates!$B$30 -> 14800.896 | P26: Four 80 GB GPUs | Q26: Published list price | R26: GCP accelerator-optimized pricing, us-central1 | S26: =C26&" | "&H26 -> Google Cloud | a2-ultragpu-4g | T26: =IF(Calculator!$D$16=Rates!$C$46,L26,IF(Calculator!$D$16=Rates!$C$47,N26,K26)) -> 20.2752 | U26: =IF(OR(Calculator!$B$13=Rates!$A$47,Calculator!$B$13=C26),1,0) -> 1 | V26: =IF(G26>=Calculator!$B$10,1,0) -> 1 | W26: =IF(AND(U26=1,V26=1),AD26,1000000000) -> 20.275201 | X26: =IF(AND(C26=Rates!$A$45,V26=1),AD26,1000000000) -> 20.275201 | Y26: =IF(AND(C26=Rates!$A$46,V26=1),AD26,1000000000) -> 1000000000 | Z26: 2039 | AA26: =Z26*F26 -> 8156 | AB26: =IFERROR(AA26/Calculator!$B$129*Rates!$B$108*Rates!$B$109,0) -> 1304.96 | AC26: =IF(Inference!$B$16<=0,1,IF(AB26<=0,1000000000,MAX(1,ROUNDUP(Inference!$B$16/AB26,0)))) -> 1 | AD26: =T26*AC26+AC26/1000000 -> 20.275201
A27: 4 | B27: A100 80 GB - larger models per GPU | C27: Google Cloud | D27: NVIDIA A100 80GB | E27: 80 | F27: 8 | G27: =E27*F27 -> 640 | H27: a2-ultragpu-8g | I27: 96 | J27: 1360 | K27: 40.5504 | L27: 16.2 | M27: Published spot rate | N27: =K27*IF(C27=Rates!$A$45,Rates!$B$29,Rates!$C$29) -> 28.38528 | O27: =K27*Rates!$B$30 -> 29601.792 | P27: Eight 80 GB GPUs, 1,360 GB RAM | Q27: Published list price | R27: GCP accelerator-optimized pricing, us-central1 | S27: =C27&" | "&H27 -> Google Cloud | a2-ultragpu-8g | T27: =IF(Calculator!$D$16=Rates!$C$46,L27,IF(Calculator!$D$16=Rates!$C$47,N27,K27)) -> 40.5504 | U27: =IF(OR(Calculator!$B$13=Rates!$A$47,Calculator!$B$13=C27),1,0) -> 1 | V27: =IF(G27>=Calculator!$B$10,1,0) -> 1 | W27: =IF(AND(U27=1,V27=1),AD27,1000000000) -> 40.550401 | X27: =IF(AND(C27=Rates!$A$45,V27=1),AD27,1000000000) -> 40.550401 | Y27: =IF(AND(C27=Rates!$A$46,V27=1),AD27,1000000000) -> 1000000000 | Z27: 2039 | AA27: =Z27*F27 -> 16312 | AB27: =IFERROR(AA27/Calculator!$B$129*Rates!$B$108*Rates!$B$109,0) -> 2609.92 | AC27: =IF(Inference!$B$16<=0,1,IF(AB27<=0,1000000000,MAX(1,ROUNDUP(Inference!$B$16/AB27,0)))) -> 1 | AD27: =T27*AC27+AC27/1000000 -> 40.550401
A28: 5 | B28: H100 NVL 94 GB - single-GPU Hopper | C28: Microsoft Azure | D28: NVIDIA H100 NVL | E28: 94 | F28: 1 | G28: =E28*F28 -> 94 | H28: Standard_NC40ads_H100_v5 | I28: 40 | J28: 320 | K28: 6.98 | L28: =K28*IF(C28=Rates!$A$45,Rates!$B$28,Rates!$C$28) -> 1.3262 | M28: Estimated (cloud default factor) | N28: =K28*IF(C28=Rates!$A$45,Rates!$B$29,Rates!$C$29) -> 4.537 | O28: =K28*Rates!$B$30 -> 5095.4 | P28: Only way to rent ONE H100 on either cloud | Q28: Published list price | R28: Azure East US / East US 2 / West US 2-3 published rate | S28: =C28&" | "&H28 -> Microsoft Azure | Standard_NC40ads_H100_v5 | T28: =IF(Calculator!$D$16=Rates!$C$46,L28,IF(Calculator!$D$16=Rates!$C$47,N28,K28)) -> 6.98 | U28: =IF(OR(Calculator!$B$13=Rates!$A$47,Calculator!$B$13=C28),1,0) -> 1 | V28: =IF(G28>=Calculator!$B$10,1,0) -> 1 | W28: =IF(AND(U28=1,V28=1),AD28,1000000000) -> 6.980001 | X28: =IF(AND(C28=Rates!$A$45,V28=1),AD28,1000000000) -> 1000000000 | Y28: =IF(AND(C28=Rates!$A$46,V28=1),AD28,1000000000) -> 6.980001 | Z28: 3900 | AA28: =Z28*F28 -> 3900 | AB28: =IFERROR(AA28/Calculator!$B$129*Rates!$B$108*Rates!$B$109,0) -> 624 | AC28: =IF(Inference!$B$16<=0,1,IF(AB28<=0,1000000000,MAX(1,ROUNDUP(Inference!$B$16/AB28,0)))) -> 1 | AD28: =T28*AC28+AC28/1000000 -> 6.980001
A29: 5 | B29: H100 NVL 94 GB - single-GPU Hopper | C29: Microsoft Azure | D29: NVIDIA H100 NVL | E29: 94 | F29: 2 | G29: =E29*F29 -> 188 | H29: Standard_NC80adis_H100_v5 | I29: 80 | J29: 640 | K29: 13.96 | L29: =K29*IF(C29=Rates!$A$45,Rates!$B$28,Rates!$C$28) -> 2.6524 | M29: Estimated (cloud default factor) | N29: =K29*IF(C29=Rates!$A$45,Rates!$B$29,Rates!$C$29) -> 9.074 | O29: =K29*Rates!$B$30 -> 10190.8 | P29: Two H100 NVL GPUs | Q29: Scaled from the 1-GPU rate | R29: Scaled 2x from NC40ads H100 v5 published rate - confirm in Azure calculator | S29: =C29&" | "&H29 -> Microsoft Azure | Standard_NC80adis_H100_v5 | T29: =IF(Calculator!$D$16=Rates!$C$46,L29,IF(Calculator!$D$16=Rates!$C$47,N29,K29)) -> 13.96 | U29: =IF(OR(Calculator!$B$13=Rates!$A$47,Calculator!$B$13=C29),1,0) -> 1 | V29: =IF(G29>=Calculator!$B$10,1,0) -> 1 | W29: =IF(AND(U29=1,V29=1),AD29,1000000000) -> 13.960001 | X29: =IF(AND(C29=Rates!$A$45,V29=1),AD29,1000000000) -> 1000000000 | Y29: =IF(AND(C29=Rates!$A$46,V29=1),AD29,1000000000) -> 13.960001 | Z29: 3900 | AA29: =Z29*F29 -> 7800 | AB29: =IFERROR(AA29/Calculator!$B$129*Rates!$B$108*Rates!$B$109,0) -> 1248 | AC29: =IF(Inference!$B$16<=0,1,IF(AB29<=0,1000000000,MAX(1,ROUNDUP(Inference!$B$16/AB29,0)))) -> 1 | AD29: =T29*AC29+AC29/1000000 -> 13.960001
A30: 6 | B30: H100 SXM 80 GB - 8-GPU training node | C30: Google Cloud | D30: NVIDIA H100 80GB SXM | E30: 80 | F30: 8 | G30: =E30*F30 -> 640 | H30: a3-highgpu-8g | I30: 208 | J30: 1872 | K30: 88.49 | L30: 29.52 | M30: Published spot rate | N30: =K30*IF(C30=Rates!$A$45,Rates!$B$29,Rates!$C$29) -> 61.943 | O30: =K30*Rates!$B$30 -> 64597.7 | P30: Large-scale training / very high volume serving | Q30: Published list price | R30: GCP accelerator-optimized pricing, us-central1 ($11.06 per GPU-hour) | S30: =C30&" | "&H30 -> Google Cloud | a3-highgpu-8g | T30: =IF(Calculator!$D$16=Rates!$C$46,L30,IF(Calculator!$D$16=Rates!$C$47,N30,K30)) -> 88.49 | U30: =IF(OR(Calculator!$B$13=Rates!$A$47,Calculator!$B$13=C30),1,0) -> 1 | V30: =IF(G30>=Calculator!$B$10,1,0) -> 1 | W30: =IF(AND(U30=1,V30=1),AD30,1000000000) -> 88.490001 | X30: =IF(AND(C30=Rates!$A$45,V30=1),AD30,1000000000) -> 88.490001 | Y30: =IF(AND(C30=Rates!$A$46,V30=1),AD30,1000000000) -> 1000000000 | Z30: 3350 | AA30: =Z30*F30 -> 26800 | AB30: =IFERROR(AA30/Calculator!$B$129*Rates!$B$108*Rates!$B$109,0) -> 4288 | AC30: =IF(Inference!$B$16<=0,1,IF(AB30<=0,1000000000,MAX(1,ROUNDUP(Inference!$B$16/AB30,0)))) -> 1 | AD30: =T30*AC30+AC30/1000000 -> 88.490001
A31: 6 | B31: H100 SXM 80 GB - 8-GPU training node | C31: Microsoft Azure | D31: NVIDIA H100 80GB SXM | E31: 80 | F31: 8 | G31: =E31*F31 -> 640 | H31: Standard_ND96isr_H100_v5 | I31: 96 | J31: 1900 | K31: 98.32 | L31: 18.169536 | M31: Published spot rate | N31: =K31*IF(C31=Rates!$A$45,Rates!$B$29,Rates!$C$29) -> 63.908 | O31: =K31*Rates!$B$30 -> 71773.6 | P31: Large-scale training with InfiniBand | Q31: Published list price | R31: Azure East US Linux pay-as-you-go (Vantage) - $12.29 per GPU-hour | S31: =C31&" | "&H31 -> Microsoft Azure | Standard_ND96isr_H100_v5 | T31: =IF(Calculator!$D$16=Rates!$C$46,L31,IF(Calculator!$D$16=Rates!$C$47,N31,K31)) -> 98.32 | U31: =IF(OR(Calculator!$B$13=Rates!$A$47,Calculator!$B$13=C31),1,0) -> 1 | V31: =IF(G31>=Calculator!$B$10,1,0) -> 1 | W31: =IF(AND(U31=1,V31=1),AD31,1000000000) -> 98.320001 | X31: =IF(AND(C31=Rates!$A$45,V31=1),AD31,1000000000) -> 1000000000 | Y31: =IF(AND(C31=Rates!$A$46,V31=1),AD31,1000000000) -> 98.320001 | Z31: 3350 | AA31: =Z31*F31 -> 26800 | AB31: =IFERROR(AA31/Calculator!$B$129*Rates!$B$108*Rates!$B$109,0) -> 4288 | AC31: =IF(Inference!$B$16<=0,1,IF(AB31<=0,1000000000,MAX(1,ROUNDUP(Inference!$B$16/AB31,0)))) -> 1 | AD31: =T31*AC31+AC31/1000000 -> 98.320001
A32: 7 | B32: H200 141 GB - biggest memory per Hopper GPU | C32: Google Cloud | D32: NVIDIA H200 141GB | E32: 141 | F32: 8 | G32: =E32*F32 -> 1128 | H32: a3-ultragpu-8g | I32: 224 | J32: 2952 | K32: 84.81 | L32: =K32*IF(C32=Rates!$A$45,Rates!$B$28,Rates!$C$28) -> 27.9873 | M32: Estimated (cloud default factor) | N32: =K32*IF(C32=Rates!$A$45,Rates!$B$29,Rates!$C$29) -> 59.367 | O32: =K32*Rates!$B$30 -> 61911.3 | P32: Very large models, long context windows | Q32: Published rate - reservation, Spot or Flex-start only | R32: GCP published rate ($10.60 per GPU-hour). A3 Ultra cannot be launched as a normal on-demand VM | S32: =C32&" | "&H32 -> Google Cloud | a3-ultragpu-8g | T32: =IF(Calculator!$D$16=Rates!$C$46,L32,IF(Calculator!$D$16=Rates!$C$47,N32,K32)) -> 84.81 | U32: =IF(OR(Calculator!$B$13=Rates!$A$47,Calculator!$B$13=C32),1,0) -> 1 | V32: =IF(G32>=Calculator!$B$10,1,0) -> 1 | W32: =IF(AND(U32=1,V32=1),AD32,1000000000) -> 84.810001 | X32: =IF(AND(C32=Rates!$A$45,V32=1),AD32,1000000000) -> 84.810001 | Y32: =IF(AND(C32=Rates!$A$46,V32=1),AD32,1000000000) -> 1000000000 | Z32: 4800 | AA32: =Z32*F32 -> 38400 | AB32: =IFERROR(AA32/Calculator!$B$129*Rates!$B$108*Rates!$B$109,0) -> 6144 | AC32: =IF(Inference!$B$16<=0,1,IF(AB32<=0,1000000000,MAX(1,ROUNDUP(Inference!$B$16/AB32,0)))) -> 1 | AD32: =T32*AC32+AC32/1000000 -> 84.810001
A33: 7 | B33: H200 141 GB - biggest memory per Hopper GPU | C33: Microsoft Azure | D33: NVIDIA H200 141GB | E33: 141 | F33: 8 | G33: =E33*F33 -> 1128 | H33: Standard_ND96isr_H200_v5 | I33: 96 | J33: 1850 | K33: 110.24 | L33: 110.24 | M33: No spot rate published for this size | N33: =K33*IF(C33=Rates!$A$45,Rates!$B$29,Rates!$C$29) -> 71.656 | O33: =K33*Rates!$B$30 -> 80475.2 | P33: Very large models, long context windows | Q33: Published list price | R33: Azure baseline (Vantage) $110.24/hr; cheapest regions list ~$84.80/hr | S33: =C33&" | "&H33 -> Microsoft Azure | Standard_ND96isr_H200_v5 | T33: =IF(Calculator!$D$16=Rates!$C$46,L33,IF(Calculator!$D$16=Rates!$C$47,N33,K33)) -> 110.24 | U33: =IF(OR(Calculator!$B$13=Rates!$A$47,Calculator!$B$13=C33),1,0) -> 1 | V33: =IF(G33>=Calculator!$B$10,1,0) -> 1 | W33: =IF(AND(U33=1,V33=1),AD33,1000000000) -> 110.24 | X33: =IF(AND(C33=Rates!$A$45,V33=1),AD33,1000000000) -> 1000000000 | Y33: =IF(AND(C33=Rates!$A$46,V33=1),AD33,1000000000) -> 110.24 | Z33: 4800 | AA33: =Z33*F33 -> 38400 | AB33: =IFERROR(AA33/Calculator!$B$129*Rates!$B$108*Rates!$B$109,0) -> 6144 | AC33: =IF(Inference!$B$16<=0,1,IF(AB33<=0,1000000000,MAX(1,ROUNDUP(Inference!$B$16/AB33,0)))) -> 1 | AD33: =T33*AC33+AC33/1000000 -> 110.24
A34: 8 | B34: MI300X 192 GB - AMD alternative | C34: Microsoft Azure | D34: AMD Instinct MI300X | E34: 192 | F34: 8 | G34: =E34*F34 -> 1536 | H34: Standard_ND96isr_MI300X_v5 | I34: 96 | J34: 1850 | K34: 62.88 | L34: =K34*IF(C34=Rates!$A$45,Rates!$B$28,Rates!$C$28) -> 11.9472 | M34: Estimated (cloud default factor) | N34: =K34*IF(C34=Rates!$A$45,Rates!$B$29,Rates!$C$29) -> 40.872 | O34: =K34*Rates!$B$30 -> 45902.4 | P34: Big-memory inference; needs ROCm not CUDA | Q34: Third-party index estimate | R34: Estimated from ~$7.86 per GPU-hour third-party index - confirm with Microsoft | S34: =C34&" | "&H34 -> Microsoft Azure | Standard_ND96isr_MI300X_v5 | T34: =IF(Calculator!$D$16=Rates!$C$46,L34,IF(Calculator!$D$16=Rates!$C$47,N34,K34)) -> 62.88 | U34: =IF(OR(Calculator!$B$13=Rates!$A$47,Calculator!$B$13=C34),1,0) -> 1 | V34: =IF(G34>=Calculator!$B$10,1,0) -> 1 | W34: =IF(AND(U34=1,V34=1),AD34,1000000000) -> 62.880001 | X34: =IF(AND(C34=Rates!$A$45,V34=1),AD34,1000000000) -> 1000000000 | Y34: =IF(AND(C34=Rates!$A$46,V34=1),AD34,1000000000) -> 62.880001 | Z34: 5300 | AA34: =Z34*F34 -> 42400 | AB34: =IFERROR(AA34/Calculator!$B$129*Rates!$B$108*Rates!$B$109,0) -> 6784 | AC34: =IF(Inference!$B$16<=0,1,IF(AB34<=0,1000000000,MAX(1,ROUNDUP(Inference!$B$16/AB34,0)))) -> 1 | AD34: =T34*AC34+AC34/1000000 -> 62.880001
A35: 9 | B35: B200 180 GB - newest Blackwell | C35: Google Cloud | D35: NVIDIA B200 180GB | E35: 180 | F35: 8 | G35: =E35*F35 -> 1440 | H35: a4-highgpu-8g | I35: 224 | J35: 3968 | K35: 39.6336 | L35: 39.6336 | M35: A4 sells only as reservation, Spot or Flex-start | N35: =K35*IF(C35=Rates!$A$45,Rates!$B$29,Rates!$C$29) -> 27.74352 | O35: =K35*Rates!$B$30 -> 28932.528 | P35: Frontier-scale training, highest throughput | Q35: Published rate - no standard on-demand | R35: About $4.95 per GPU-hour. Trackers range $34-40/hr for the node; A4 cannot be launched as a normal on-demand VM | S35: =C35&" | "&H35 -> Google Cloud | a4-highgpu-8g | T35: =IF(Calculator!$D$16=Rates!$C$46,L35,IF(Calculator!$D$16=Rates!$C$47,N35,K35)) -> 39.6336 | U35: =IF(OR(Calculator!$B$13=Rates!$A$47,Calculator!$B$13=C35),1,0) -> 1 | V35: =IF(G35>=Calculator!$B$10,1,0) -> 1 | W35: =IF(AND(U35=1,V35=1),AD35,1000000000) -> 39.633601 | X35: =IF(AND(C35=Rates!$A$45,V35=1),AD35,1000000000) -> 39.633601 | Y35: =IF(AND(C35=Rates!$A$46,V35=1),AD35,1000000000) -> 1000000000 | Z35: 8000 | AA35: =Z35*F35 -> 64000 | AB35: =IFERROR(AA35/Calculator!$B$129*Rates!$B$108*Rates!$B$109,0) -> 10240 | AC35: =IF(Inference!$B$16<=0,1,IF(AB35<=0,1000000000,MAX(1,ROUNDUP(Inference!$B$16/AB35,0)))) -> 1 | AD35: =T35*AC35+AC35/1000000 -> 39.633601
A37: Notes: (1) A 'Tier' is a group of machines built on the same class of GPU; tier 1 is the cheapest hardware, tier 9 the most powerful.
A38: (2) Some machines are sold only as a full 8-GPU node - you pay for all eight even if you use one. Those rows say '8' in 'GPUs per machine'.
A39: (3) Spot machines can be shut down by the cloud with about 30 seconds' notice. They are for work that can be interrupted and restarted.
A40: (4) Rows marked 'Scaled from the 1-GPU rate' or 'estimate' are not published prices. Confirm them in the provider's own calculator before you commit budget.
A41: (5) GPU quota starts at zero on both clouds. Getting approved to launch these machines can take days to weeks for the top tiers.

Sheet Sizing_Guide
A1: How much GPU memory does a model need?
A2: A rough rule: memory = parameters x bytes per parameter, plus headroom for the conversation cache. This table uses the headroom percentage from the Calculator tab, so it moves when you change it.
A4: Model size (billions of parameters) | B4: Example | C4: FP16 - GB needed | D4: FP8 / INT8 - GB needed | E4: INT4 - GB needed | F4: Smallest machine that fits at FP16
A5: 1 | B5: Tiny on-device models | C5: =ROUNDUP($A5*2*(1+Calculator!$B$8),0) -> 3 | D5: =ROUNDUP($A5*1*(1+Calculator!$B$8),0) -> 2 | E5: =ROUNDUP($A5*0.5*(1+Calculator!$B$8),0) -> 1 | F5: =IF($C5<=16,"1x T4 (16 GB) - tier 1",IF($C5<=24,"1x L4 or A10 (24 GB) - tier 2",IF($C5<=40,"1x A100 40GB - tier 3",IF($C5<=80,"1x A100 80GB - tier 4",IF($C5<=94,"1x H100 NVL 94GB - tier 5",IF($C5<=192,"8x L4 node (192 GB), or 2x H100 NVL if under 188 GB",IF($C5<=320,"4x A100 80GB (320 GB) - tier 4",IF($C5<=640,"8x A100 80GB or 8x H100 node (640 GB)",IF($C5<=1128,"8x H200 node (1,128 GB) - tier 7",IF($C5<=1440,"8x B200 node (1,440 GB) - tier 9",IF($C5<=1536,"8x MI300X node (1,536 GB) - tier 8","More than one machine needed"))))))))))) -> 1x T4 (16 GB) - tier 1
A6: 3 | B6: Small assistants, classifiers | C6: =ROUNDUP($A6*2*(1+Calculator!$B$8),0) -> 8 | D6: =ROUNDUP($A6*1*(1+Calculator!$B$8),0) -> 4 | E6: =ROUNDUP($A6*0.5*(1+Calculator!$B$8),0) -> 2 | F6: =IF($C6<=16,"1x T4 (16 GB) - tier 1",IF($C6<=24,"1x L4 or A10 (24 GB) - tier 2",IF($C6<=40,"1x A100 40GB - tier 3",IF($C6<=80,"1x A100 80GB - tier 4",IF($C6<=94,"1x H100 NVL 94GB - tier 5",IF($C6<=192,"8x L4 node (192 GB), or 2x H100 NVL if under 188 GB",IF($C6<=320,"4x A100 80GB (320 GB) - tier 4",IF($C6<=640,"8x A100 80GB or 8x H100 node (640 GB)",IF($C6<=1128,"8x H200 node (1,128 GB) - tier 7",IF($C6<=1440,"8x B200 node (1,440 GB) - tier 9",IF($C6<=1536,"8x MI300X node (1,536 GB) - tier 8","More than one machine needed"))))))))))) -> 1x T4 (16 GB) - tier 1
A7: 7 | B7: Mistral 7B class | C7: =ROUNDUP($A7*2*(1+Calculator!$B$8),0) -> 19 | D7: =ROUNDUP($A7*1*(1+Calculator!$B$8),0) -> 10 | E7: =ROUNDUP($A7*0.5*(1+Calculator!$B$8),0) -> 5 | F7: =IF($C7<=16,"1x T4 (16 GB) - tier 1",IF($C7<=24,"1x L4 or A10 (24 GB) - tier 2",IF($C7<=40,"1x A100 40GB - tier 3",IF($C7<=80,"1x A100 80GB - tier 4",IF($C7<=94,"1x H100 NVL 94GB - tier 5",IF($C7<=192,"8x L4 node (192 GB), or 2x H100 NVL if under 188 GB",IF($C7<=320,"4x A100 80GB (320 GB) - tier 4",IF($C7<=640,"8x A100 80GB or 8x H100 node (640 GB)",IF($C7<=1128,"8x H200 node (1,128 GB) - tier 7",IF($C7<=1440,"8x B200 node (1,440 GB) - tier 9",IF($C7<=1536,"8x MI300X node (1,536 GB) - tier 8","More than one machine needed"))))))))))) -> 1x L4 or A10 (24 GB) - tier 2
A8: 8 | B8: Llama 3 8B class | C8: =ROUNDUP($A8*2*(1+Calculator!$B$8),0) -> 21 | D8: =ROUNDUP($A8*1*(1+Calculator!$B$8),0) -> 11 | E8: =ROUNDUP($A8*0.5*(1+Calculator!$B$8),0) -> 6 | F8: =IF($C8<=16,"1x T4 (16 GB) - tier 1",IF($C8<=24,"1x L4 or A10 (24 GB) - tier 2",IF($C8<=40,"1x A100 40GB - tier 3",IF($C8<=80,"1x A100 80GB - tier 4",IF($C8<=94,"1x H100 NVL 94GB - tier 5",IF($C8<=192,"8x L4 node (192 GB), or 2x H100 NVL if under 188 GB",IF($C8<=320,"4x A100 80GB (320 GB) - tier 4",IF($C8<=640,"8x A100 80GB or 8x H100 node (640 GB)",IF($C8<=1128,"8x H200 node (1,128 GB) - tier 7",IF($C8<=1440,"8x B200 node (1,440 GB) - tier 9",IF($C8<=1536,"8x MI300X node (1,536 GB) - tier 8","More than one machine needed"))))))))))) -> 1x L4 or A10 (24 GB) - tier 2
A9: 13 | B9: Older 13B chat models | C9: =ROUNDUP($A9*2*(1+Calculator!$B$8),0) -> 34 | D9: =ROUNDUP($A9*1*(1+Calculator!$B$8),0) -> 17 | E9: =ROUNDUP($A9*0.5*(1+Calculator!$B$8),0) -> 9 | F9: =IF($C9<=16,"1x T4 (16 GB) - tier 1",IF($C9<=24,"1x L4 or A10 (24 GB) - tier 2",IF($C9<=40,"1x A100 40GB - tier 3",IF($C9<=80,"1x A100 80GB - tier 4",IF($C9<=94,"1x H100 NVL 94GB - tier 5",IF($C9<=192,"8x L4 node (192 GB), or 2x H100 NVL if under 188 GB",IF($C9<=320,"4x A100 80GB (320 GB) - tier 4",IF($C9<=640,"8x A100 80GB or 8x H100 node (640 GB)",IF($C9<=1128,"8x H200 node (1,128 GB) - tier 7",IF($C9<=1440,"8x B200 node (1,440 GB) - tier 9",IF($C9<=1536,"8x MI300X node (1,536 GB) - tier 8","More than one machine needed"))))))))))) -> 1x A100 40GB - tier 3
A10: 32 | B10: Qwen 32B class | C10: =ROUNDUP($A10*2*(1+Calculator!$B$8),0) -> 84 | D10: =ROUNDUP($A10*1*(1+Calculator!$B$8),0) -> 42 | E10: =ROUNDUP($A10*0.5*(1+Calculator!$B$8),0) -> 21 | F10: =IF($C10<=16,"1x T4 (16 GB) - tier 1",IF($C10<=24,"1x L4 or A10 (24 GB) - tier 2",IF($C10<=40,"1x A100 40GB - tier 3",IF($C10<=80,"1x A100 80GB - tier 4",IF($C10<=94,"1x H100 NVL 94GB - tier 5",IF($C10<=192,"8x L4 node (192 GB), or 2x H100 NVL if under 188 GB",IF($C10<=320,"4x A100 80GB (320 GB) - tier 4",IF($C10<=640,"8x A100 80GB or 8x H100 node (640 GB)",IF($C10<=1128,"8x H200 node (1,128 GB) - tier 7",IF($C10<=1440,"8x B200 node (1,440 GB) - tier 9",IF($C10<=1536,"8x MI300X node (1,536 GB) - tier 8","More than one machine needed"))))))))))) -> 1x H100 NVL 94GB - tier 5
A11: 124 | B11: Llama 3 70B class | C11: =ROUNDUP($A11*2*(1+Calculator!$B$8),0) -> 323 | D11: =ROUNDUP($A11*1*(1+Calculator!$B$8),0) -> 162 | E11: =ROUNDUP($A11*0.5*(1+Calculator!$B$8),0) -> 81 | F11: =IF($C11<=16,"1x T4 (16 GB) - tier 1",IF($C11<=24,"1x L4 or A10 (24 GB) - tier 2",IF($C11<=40,"1x A100 40GB - tier 3",IF($C11<=80,"1x A100 80GB - tier 4",IF($C11<=94,"1x H100 NVL 94GB - tier 5",IF($C11<=192,"8x L4 node (192 GB), or 2x H100 NVL if under 188 GB",IF($C11<=320,"4x A100 80GB (320 GB) - tier 4",IF($C11<=640,"8x A100 80GB or 8x H100 node (640 GB)",IF($C11<=1128,"8x H200 node (1,128 GB) - tier 7",IF($C11<=1440,"8x B200 node (1,440 GB) - tier 9",IF($C11<=1536,"8x MI300X node (1,536 GB) - tier 8","More than one machine needed"))))))))))) -> 8x A100 80GB or 8x H100 node (640 GB)
A12: 123 | B12: Mistral Large class | C12: =ROUNDUP($A12*2*(1+Calculator!$B$8),0) -> 320 | D12: =ROUNDUP($A12*1*(1+Calculator!$B$8),0) -> 160 | E12: =ROUNDUP($A12*0.5*(1+Calculator!$B$8),0) -> 80 | F12: =IF($C12<=16,"1x T4 (16 GB) - tier 1",IF($C12<=24,"1x L4 or A10 (24 GB) - tier 2",IF($C12<=40,"1x A100 40GB - tier 3",IF($C12<=80,"1x A100 80GB - tier 4",IF($C12<=94,"1x H100 NVL 94GB - tier 5",IF($C12<=192,"8x L4 node (192 GB), or 2x H100 NVL if under 188 GB",IF($C12<=320,"4x A100 80GB (320 GB) - tier 4",IF($C12<=640,"8x A100 80GB or 8x H100 node (640 GB)",IF($C12<=1128,"8x H200 node (1,128 GB) - tier 7",IF($C12<=1440,"8x B200 node (1,440 GB) - tier 9",IF($C12<=1536,"8x MI300X node (1,536 GB) - tier 8","More than one machine needed"))))))))))) -> 4x A100 80GB (320 GB) - tier 4
A13: 405 | B13: Llama 3.1 405B class | C13: =ROUNDUP($A13*2*(1+Calculator!$B$8),0) -> 1053 | D13: =ROUNDUP($A13*1*(1+Calculator!$B$8),0) -> 527 | E13: =ROUNDUP($A13*0.5*(1+Calculator!$B$8),0) -> 264 | F13: =IF($C13<=16,"1x T4 (16 GB) - tier 1",IF($C13<=24,"1x L4 or A10 (24 GB) - tier 2",IF($C13<=40,"1x A100 40GB - tier 3",IF($C13<=80,"1x A100 80GB - tier 4",IF($C13<=94,"1x H100 NVL 94GB - tier 5",IF($C13<=192,"8x L4 node (192 GB), or 2x H100 NVL if under 188 GB",IF($C13<=320,"4x A100 80GB (320 GB) - tier 4",IF($C13<=640,"8x A100 80GB or 8x H100 node (640 GB)",IF($C13<=1128,"8x H200 node (1,128 GB) - tier 7",IF($C13<=1440,"8x B200 node (1,440 GB) - tier 9",IF($C13<=1536,"8x MI300X node (1,536 GB) - tier 8","More than one machine needed"))))))))))) -> 8x H200 node (1,128 GB) - tier 7
A14: 671 | B14: DeepSeek V3 class | C14: =ROUNDUP($A14*2*(1+Calculator!$B$8),0) -> 1745 | D14: =ROUNDUP($A14*1*(1+Calculator!$B$8),0) -> 873 | E14: =ROUNDUP($A14*0.5*(1+Calculator!$B$8),0) -> 437 | F14: =IF($C14<=16,"1x T4 (16 GB) - tier 1",IF($C14<=24,"1x L4 or A10 (24 GB) - tier 2",IF($C14<=40,"1x A100 40GB - tier 3",IF($C14<=80,"1x A100 80GB - tier 4",IF($C14<=94,"1x H100 NVL 94GB - tier 5",IF($C14<=192,"8x L4 node (192 GB), or 2x H100 NVL if under 188 GB",IF($C14<=320,"4x A100 80GB (320 GB) - tier 4",IF($C14<=640,"8x A100 80GB or 8x H100 node (640 GB)",IF($C14<=1128,"8x H200 node (1,128 GB) - tier 7",IF($C14<=1440,"8x B200 node (1,440 GB) - tier 9",IF($C14<=1536,"8x MI300X node (1,536 GB) - tier 8","More than one machine needed"))))))))))) -> More than one machine needed
A17: Things this rule of thumb does not capture:
A18: - Very long context windows (100k+ tokens) can double or triple the cache, so add more headroom.
A19: - Many simultaneous users also grows the cache. If you expect heavy traffic, size up a tier.
A20: - Training or fine-tuning a model needs roughly three to four times the memory of just serving it.
A21: - A model can be split across several GPUs in one machine, which is why the 8-GPU nodes show such large totals.
A22: - Quantising to INT4 saves a lot of money but does cost some answer quality. Test before you commit.
A23: - H200, MI300X and B200 are sold only as full eight-GPU machines - and on Google Cloud the H200 and B200 families cannot be launched as normal on-demand VMs at all; they need a reservation, Spot, or Flex-start.

Sheet Rates
A1: Rate Card and Assumptions
A2: All rates are US-region list prices in US dollars, checked August 2026. Blue numbers are assumptions or rates you may change. See the Sources tab.
A4: A. STORAGE - price per GB per month
A5: Storage option | B5: Google Cloud $/GB-mo | C5: Microsoft Azure $/GB-mo | D5: What this maps to
A6: Economy (HDD) | B6: 0.04 | C6: 0.046 | D6: GCP Standard persistent disk / Azure Standard HDD
A7: Standard SSD | B7: 0.1 | C7: 0.048 | D7: GCP Balanced persistent disk / Azure Standard SSD
A8: Balanced SSD (recommended) | B8: 0.1 | C8: 0.081 | D8: GCP Balanced persistent disk / Azure Premium SSD v2
A9: High performance SSD | B9: 0.17 | C9: 0.132 | D9: GCP SSD persistent disk / Azure Premium SSD (P30-class)
A11: B. DATA TRANSFER OUT (egress) - price per GB per month
A12: Band | B12: Google Cloud (Premium tier) | C12: Microsoft Azure | D12: Notes
A13: Free allowance (GB per month) | B13: 1 | C13: 100 | D13: Azure gives a far bigger free allowance
A14: First 1 TB (1,024 GB) $/GB | B14: 0.12 | C14: 0.087 | D14: GCP Standard-tier networking is cheaper (~$0.085) if you can use it
A15: Next 9 TB (up to 10 TB) $/GB | B15: 0.11 | C15: 0.087 | D15: Azure is flat across this range
A16: Above 10 TB $/GB | B16: 0.08 | C16: 0.087 | D16: Azure discounts further above ~150 TB/month (not modelled)
A17: Tiers apply to total monthly volume; the free allowance is a credit inside the first tier, not an extra slice on top of it.
A19: C. REGION PRICE UPLIFT - multiplier applied to the machine rate
A20: Region | B20: Google Cloud | C20: Microsoft Azure | D20: Notes
A21: US (baseline) | B21: 1 | C21: 1 | D21: us-central1 / East US - the cheapest and the basis of every rate here
A22: Western Europe | B22: 1.1 | C22: 1.19 | D22: Approximate. Azure West Europe runs about 19% above East US
A23: Asia-Pacific | B23: 1.15 | C23: 1.3 | D23: Approximate. Southeast Asia runs about 30% above East US on Azure
A24: Australia | B24: 1.15 | C24: 1.33 | D24: Approximate. Australia East runs about 33% above East US on Azure
A26: D. DISCOUNT AND TIME ASSUMPTIONS
A27: Assumption | B27: Google Cloud | C27: Microsoft Azure | D27: Notes
A28: Spot price factor (used only where no spot rate is published) | B28: 0.33 | C28: 0.19 | D28: GCP spot is typically 60-91% off; Azure spot 70-82% off. These are mid-range.
A29: 1-Year commitment factor (share of on-demand you still pay) | B29: 0.7 | C29: 0.65 | D29: GCP committed-use ~25-37% off; Azure 1-yr reserved ~35% off. GPU discounts are shallower than CPU.
A30: Billable hours in an average month | B30: 730 | D30: 730 = 24 x 365 / 12. Used for the monthly column on the price list.
A32: E. MANAGED AI PLATFORM UPLIFT - added to the compute cost
A33: Cloud | B33: Uplift on compute | D33: Notes
A34: Google Cloud | B34: 0.26 | D34: Vertex AI training charges roughly 26% above the raw Compute Engine rate
A35: Microsoft Azure | B35: 0.25 | D35: Azure Machine Learning compute runs roughly 25% above the raw VM rate
A37: F. MODEL MEMORY - bytes of GPU memory per parameter
A38: Precision | B38: Bytes per parameter | D38: Notes
A39: FP16 / BF16 - best quality | B39: 2 | D39: Full quality. Standard for training and quality-critical serving.
A40: FP8 / INT8 - balanced | B40: 1 | D40: Half the memory, very little quality loss for most tasks.
A41: INT4 - smallest and cheapest | B41: 0.5 | D41: Quarter the memory. Some quality loss; very popular for serving.
A43: G. DROPDOWN LISTS - used by the Calculator tab. Do not edit or reorder.
A44: Cloud | B44: Region | C44: Pricing model | D44: Storage option | E44: Precision | F44: Managed service | G44: Machine choice | H44: Support level | I44: Inference sizing
A45: Google Cloud | B45: US (baseline) | C45: On-demand (pay as you go) | D45: Economy (HDD) | E45: FP16 / BF16 - best quality | F45: No - plain virtual machines | G45: Auto - cheapest that fits | H45: Use the recommendation | I45: Yes - size the machines for this traffic
A46: Microsoft Azure | B46: Western Europe | C46: Spot (interruptible, cheapest) | D46: Standard SSD | E46: FP8 / INT8 - balanced | F46: Yes - managed AI platform | G46: Microsoft Azure | Standard_NC4as_T4_v3 | H46: Low | I46: No - ignore traffic, size on memory only
A47: Compare both | B47: Asia-Pacific | C47: 1-Year commitment | D47: Balanced SSD (recommended) | E47: INT4 - smallest and cheapest | G47: Google Cloud | n1-standard-4 + 1x T4 | H47: Medium
B48: Australia | D48: High performance SSD | G48: Google Cloud | n1-standard-8 + 1x T4 | H48: High
G49: Microsoft Azure | Standard_NC8as_T4_v3
G50: Google Cloud | n1-standard-8 + 2x T4
G51: Google Cloud | g2-standard-4
G52: Google Cloud | g2-standard-8
G53: Google Cloud | g2-standard-24
G54: Microsoft Azure | Standard_NV36ads_A10_v5
G55: Google Cloud | g2-standard-48
G56: Google Cloud | g2-standard-96
G57: Google Cloud | a2-highgpu-1g
G58: Google Cloud | a2-highgpu-2g
G59: Google Cloud | a2-highgpu-4g
G60: Google Cloud | a2-highgpu-8g
... G76: Google Cloud | a4-highgpu-8g
A78: H. LABOUR / SUPPORT COST - the people who keep the model running
A79: Support level | B79: Engineer hours per month | C79: Recommended for | D79: What this level typically covers
A80: Low | B80: 20 | C80: Small models - up to 13 billion parameters | D80: Keeping the lights on: patching, monitoring alerts, occasional restarts. Roughly half a day a week.
A81: Medium | B81: 60 | C81: Medium models - 14 to 70 billion parameters | D81: The above plus tuning, capacity changes, incident response and version upgrades. Roughly one and a half days a week.
A82: High | B82: 160 | C82: Large models - more than 70 billion parameters | D82: A dedicated engineer: multi-GPU orchestration, performance work, on-call cover, cost control. About one full-time person.
A83: Engineer cost per hour ($) | B83: =Calculator!$B$33 -> 116 | D83: Set on the Calculator tab, step 5. Shown here for reference only.
A84: Size threshold - Low support applies up to (billion parameters) | B84: 13 | D84: Models at or below this size get the Low recommendation.
A85: Size threshold - Medium support applies up to (billion parameters) | B85: 70 | D85: Above this size the recommendation becomes High.
A87: I. SIMPLE_CALC TRANSLATION - how the three plain-English answers become settings
A88: Step 1 answer - how big is the model | B88: Billions of parameters | C88: Disk GB per copy | D88: Notes
A89: Small - simple chatbot, classifying or tagging text, autocomplete | B89: 8 | C89: 200 | D89: 8B class, e.g. Llama 3 8B
A90: Medium - a capable general-purpose assistant | B90: 32 | C90: 300 | D90: 32B class, e.g. Qwen 32B
A91: Large - top-tier assistant, complex reasoning and long documents | B91: 70 | C91: 500 | D91: 70B class, e.g. Llama 3 70B
A92: Very large - frontier-class, the biggest open models available | B92: 405 | C92: 2000 | D92: 405B class, e.g. Llama 3.1 405B
A94: Step 2 answer - how much use | B94: Hours per day | C94: Days per month | D94: Copies of the model | E94: Data out GB per month
A95: Just me or a few people, trying it out | B95: 8 | C95: 22 | D95: 1 | E95: 100
A96: One team, during working hours only | B96: 10 | C96: 22 | D96: 1 | E96: 500
A97: A whole department, running around the clock | B97: 24 | C97: 30.42 | D97: 1 | E97: 2000
A98: Customer-facing service, around the clock, with a spare copy | B98: 24 | C98: 30.42 | D98: 2 | E98: 10000
A100: Step 3 answer - what matters most | B100: Precision | C100: Pricing model | D100: Managed platform | E100: Notes
A101: Lowest possible cost | B101: INT4 - smallest and cheapest | C101: Spot (interruptible, cheapest) | D101: No - plain virtual machines | E101: Smallest memory footprint and interruptible machines - cheapest, some quality and reliability trade-off
A102: A balance of cost and reliability | B102: FP8 / INT8 - balanced | C102: On-demand (pay as you go) | D102: No - plain virtual machines | E102: Half-precision and normal pay-as-you-go machines - the sensible middle
A103: Reliability and answer quality above all | B103: FP16 / BF16 - best quality | C103: 1-Year commitment | D103: Yes - managed AI platform | E103: Full precision, a committed 1-year rate, and a managed platform to reduce the chance of mistakes
A106: J. INFERENCE THROUGHPUT ASSUMPTIONS - how fast one machine can generate tokens
A107: Assumption | B107: Value | D107: Notes
A108: Batching gain | B108: 16 | D108: Serving many requests at once reads the weights once for the whole batch. 16 is a realistic gain for a well-tuned server (vLLM / TensorRT-LLM); drop to 4-8 for a naive setup.
A109: Useful utilisation of peak bandwidth | B109: 0.7 | D109: No server reaches theoretical bandwidth. 0.70 is a common real-world figure.
A110: Prefill speed advantage over decode | B110: 10 | D110: Reading a prompt is compute-bound and far faster per token than generating one. Input tokens are charged at one tenth the cost of an output token.
A111: K. HOSTED PAY-PER-TOKEN MODELS - price per 1 million tokens, August 2026
A112: Sorted cheapest first within each platform. Columns I to K are used by the Calculator and Comparison tabs - please leave them alone.
A113: Model | B113: Runs on | C113: Model provider | D113: $ per 1M input | E113: $ per 1M output | F113: Context window | G113: Good for | H113: Price confidence | I113: Cost/month at your traffic | J113: Rank - Google Cloud | K113: Rank - Azure
A114: Gemini 2.5 Flash-Lite | B114: Google Cloud | C114: Google | D114: 0.1 | E114: 0.4 | F114: 1M | G114: Cheapest option anywhere. Classification, tagging, extraction | H114: Published - RETIRES 16 Oct 2026 | I114: =Inference!$B$7*Inference!$B$8/1000000*$D$114+Inference!$B$7*Inference!$B$9/1000000*$E$114 -> 120 | J114: =IF($B$114=$A$45,$I$114,1000000000) -> 120 | K114: =IF($B$114=$A$46,$I$114,1000000000) -> 1000000000
A115: Gemini 3.1 Flash-Lite | B115: Google Cloud | C115: Google | D115: 0.25 | E115: 1.5 | F115: 1M | G115: High-volume production on the current generation | H115: Published list price | I115: =Inference!$B$7*Inference!$B$8/1000000*$D$115+Inference!$B$7*Inference!$B$9/1000000*$E$115 -> 400 | J115: =IF($B$115=$A$45,$I$115,1000000000) -> 400 | K115: =IF($B$115=$A$46,$I$115,1000000000) -> 1000000000
A116: Gemini 3.5 Flash-Lite | B116: Google Cloud | C116: Google | D116: 0.3 | E116: 2.5 | F116: 1M | G116: High volume where newer model behaviour matters | H116: Published list price | I116: =Inference!$B$7*Inference!$B$8/1000000*$D$116+Inference!$B$7*Inference!$B$9/1000000*$E$116 -> 620 | J116: =IF($B$116=$A$45,$I$116,1000000000) -> 620 | K116: =IF($B$116=$A$46,$I$116,1000000000) -> 1000000000
A117: Gemini 3 Flash | B117: Google Cloud | C117: Google | D117: 0.5 | E117: 3 | F117: 1M | G117: Balanced speed and capability, previous generation | H117: Published list price | I117: =Inference!$B$7*Inference!$B$8/1000000*$D$117+Inference!$B$7*Inference!$B$9/1000000*$E$117 -> 800 | J117: =IF($B$117=$A$45,$I$117,1000000000) -> 800 | K117: =IF($B$117=$A$46,$I$117,1000000000) -> 1000000000
A118: Gemini 3.7 Flash | B118: Google Cloud | C118: Google | D118: 0.75 | E118: 3.75 | F118: 1M | G118: Current default workhorse. Introductory rate | H118: Intro price to 31 Dec 2026, then $1.50/$7.50 | I118: =Inference!$B$7*Inference!$B$8/1000000*$D$118+Inference!$B$7*Inference!$B$9/1000000*$E$118 -> 1050 | J118: =IF($B$118=$A$45,$I$118,1000000000) -> 1050 | K118: =IF($B$118=$A$46,$I$118,1000000000) -> 1000000000
A119: Gemini 3.6 Flash | B119: Google Cloud | C119: Google | D119: 0.75 | E119: 3.75 | F119: 1M | G119: Workhorse tier, introductory rate | H119: Intro price to 31 Dec 2026, then $1.50/$7.50 | I119: =Inference!$B$7*Inference!$B$8/1000000*$D$119+Inference!$B$7*Inference!$B$9/1000000*$E$119 -> 1050 | J119: =IF($B$119=$A$45,$I$119,1000000000) -> 1050 | K119: =IF($B$119=$A$46,$I$119,1000000000) -> 1000000000
A120: Claude Haiku 4.5 (Vertex AI) | B120: Google Cloud | C120: Anthropic | D120: 1 | E120: 5 | F120: 200K | G120: Fast, cheap Claude for extraction and routing | H120: Published list price | I120: =Inference!$B$7*Inference!$B$8/1000000*$D$120+Inference!$B$7*Inference!$B$9/1000000*$E$120 -> 1400 | J120: =IF($B$120=$A$45,$I$120,1000000000) -> 1400 | K120: =IF($B$120=$A$46,$I$120,1000000000) -> 1000000000
A121: Gemini 3.5 Flash | B121: Google Cloud | C121: Google | D121: 1.5 | E121: 9 | F121: 1M | G121: Frontier-class speed tier with grounding | H121: Published list price | I121: =Inference!$B$7*Inference!$B$8/1000000*$D$121+Inference!$B$7*Inference!$B$9/1000000*$E$121 -> 2400 | J121: =IF($B$121=$A$45,$I$121,1000000000) -> 2400 | K121: =IF($B$121=$A$46,$I$121,1000000000) -> 1000000000
A122: Claude Sonnet 5 (Vertex AI) | B122: Google Cloud | C122: Anthropic | D122: 2 | E122: 10 | F122: 1M | G122: Best price-performance Claude. Agentic work, coding | H122: Published list price | I122: =Inference!$B$7*Inference!$B$8/1000000*$D$122+Inference!$B$7*Inference!$B$9/1000000*$E$122 -> 2800 | J122: =IF($B$122=$A$45,$I$122,1000000000) -> 2800 | K122: =IF($B$122=$A$46,$I$122,1000000000) -> 1000000000
A123: Gemini 3.1 Pro | B123: Google Cloud | C123: Google | D123: 2 | E123: 12 | F123: 1M | G123: Google flagship reasoning. $4/$18 above 200K tokens | H123: Published list price | I123: =Inference!$B$7*Inference!$B$8/1000000*$D$123+Inference!$B$7*Inference!$B$9/1000000*$E$123 -> 3200 | J123: =IF($B$123=$A$45,$I$123,1000000000) -> 3200 | K123: =IF($B$123=$A$46,$I$123,1000000000) -> 1000000000
A124: Claude Opus 5 (Vertex AI) | B124: Google Cloud | C124: Anthropic | D124: 5 | E124: 25 | F124: 1M | G124: Hardest reasoning, long-running agents | H124: Published list price | I124: =Inference!$B$7*Inference!$B$8/1000000*$D$124+Inference!$B$7*Inference!$B$9/1000000*$E$124 -> 7000 | J124: =IF($B$124=$A$45,$I$124,1000000000) -> 7000 | K124: =IF($B$124=$A$46,$I$124,1000000000) -> 1000000000
A125: GPT-5.6 Luna | B125: Microsoft Azure | C125: OpenAI | D125: 0.2 | E125: 1.2 | F125: 1.05M | G125: Cheapest GPT-5.6 tier. High-volume work | H125: List parity with OpenAI from 1 Aug 2026 - SEE BILLING NOTE | I125: =Inference!$B$7*Inference!$B$8/1000000*$D$125+Inference!$B$7*Inference!$B$9/1000000*$E$125 -> 320 | J125: =IF($B$125=$A$45,$I$125,1000000000) -> 1000000000 | K125: =IF($B$125=$A$46,$I$125,1000000000) -> 320
A126: GPT-5.4 mini | B126: Microsoft Azure | C126: OpenAI | D126: 0.75 | E126: 4.5 | F126: 400K | G126: Small previous-generation model | H126: Published list price | I126: =Inference!$B$7*Inference!$B$8/1000000*$D$126+Inference!$B$7*Inference!$B$9/1000000*$E$126 -> 1200 | J126: =IF($B$126=$A$45,$I$126,1000000000) -> 1000000000 | K126: =IF($B$126=$A$46,$I$126,1000000000) -> 1200
A127: Claude Haiku 4.5 (Foundry) | B127: Microsoft Azure | C127: Anthropic | D127: 1 | E127: 5 | F127: 200K | G127: Fast, cheap Claude on Azure | H127: Published list price | I127: =Inference!$B$7*Inference!$B$8/1000000*$D$127+Inference!$B$7*Inference!$B$9/1000000*$E$127 -> 1400 | J127: =IF($B$127=$A$45,$I$127,1000000000) -> 1000000000 | K127: =IF($B$127=$A$46,$I$127,1000000000) -> 1400
A128: GPT-5.1 | B128: Microsoft Azure | C128: OpenAI | D128: 1.25 | E128: 10 | F128: 1M | G128: Older family, still on the price sheet | H128: Published list price | I128: =Inference!$B$7*Inference!$B$8/1000000*$D$128+Inference!$B$7*Inference!$B$9/1000000*$E$128 -> 2500 | J128: =IF($B$128=$A$45,$I$128,1000000000) -> 1000000000 | K128: =IF($B$128=$A$46,$I$128,1000000000) -> 2500
...

Sheet Read_Me
A1: Read me first
A3: What this workbook does
A4: It estimates the monthly cost of running a large language model on your own cloud machines, on either Google Cloud or Microsoft Azure. It compares the two, shows you the cheapest machine that is big enough for your model, and adds the cost of the people needed to support it.
A6: How to use it - the short way
A7: Open the Simple_Calc tab. It is the first one. Answer three questions from drop-down lists and read the total. That is all most people need.
A8: Your three answers are sent to the Calculator tab automatically, so both tabs always agree.
A10: How to use it - the detailed way
A11: 1. Open the Calculator tab. Rows marked >> arrive from Simple_Calc; every other yellow box is yours to set - region, cloud, disk type, support level.
A12: 2. Rows marked >> start blank and borrow their value from Simple_Calc. Type into one and your value takes over that row immediately. Clear it and the row goes back to following Simple_Calc.
A13: 3. The 'Value in use' and 'Coming from' columns on the right always show which number the estimate is using and where it came from, so nothing changes silently.
A14: 4. Read your answer in step 6, at the bottom of the tab.
A15: 5. Open the Comparison tab to see Google Cloud and Azure side by side for the same requirement.
... A53: These are published list prices for US regions, checked in August 2026. Cloud GPU prices move often and vary by region and by what your organisation has negotiated. Rows on the price list marked 'scaled' or 'estimate' are not published prices - check those in the provider's own calculator before you commit budget. Treat the total as a planning figure with a margin of error, not a quote.

Sheet Sources
A1: Sources and change log
A2: Every rate in this workbook traces to one of the sources below. GPU and hosted-model rates re-verified 2 September 2026.
A4: What it covers | B4: Source | C4: Date checked | D4: Notes
A5: Google Cloud GPU machine rates (G2/L4, A2/A100, A3/H100) | B5: cloud.google.com/products/compute/pricing/accelerator-optimized + the pricing.yml in your archive | C5: Aug 2026 | D5: The archive's April 2025 figures still match today's published rates exactly, so they were kept.
A6: Google Cloud H200 (a3-ultragpu-8g) and B200 (a4-highgpu-8g) | B6: Google Cloud pricing page; DevZero, CloudPrice, Spheron, IntuitionLabs trackers | C6: Aug 2026 | D6: Neither family launches as a normal on-demand VM - reservation, Spot or Flex-start only. B200 node rate $39.63/hr (trackers range $34-40); B200 on A4 exposes 180 GB per GPU, 1,440 GB per node.
A7: Google Cloud spot and committed-use discount ranges | B7: cloud.google.com/products/compute/gpus-pricing | C7: Aug 2026 | D7: Spot is 60-91% off and can change monthly. Committed use is 25-37% off for one year.
A8: Google Cloud disk prices ($0.04 / $0.10 / $0.17 per GB-month) | B8: cloud.google.com/compute/disks-image-pricing, us-central1 | C8: Aug 2026 | D8: Standard, Balanced and SSD persistent disk.
A9: Google Cloud egress ($0.12 / $0.11 / $0.08 per GB, 1 GB free) | B9: Google Cloud network pricing; cross-checked against egresscost.com | C9: Jun 2026 | D9: Premium tier. Standard tier is about $0.085/GB with 200 GiB free if you can use it.
A10: Azure T4, A10, A100 80GB, H100 and H200 VM rates | B10: instances.vantage.sh and cloudprice.net, East US / East US 2 Linux pay-as-you-go | C10: Jul-Aug 2026 | D10: Published spot rates were used where they exist. ND H200 v5 has no published spot rate.
A11: Azure NC48ads / NC96ads A100 v4 and NC80adis H100 v5 | B11: Scaled from the published single-GPU rate | C11: Aug 2026 | D11: Not a published figure. Confirm in the Azure pricing calculator.
A12: Azure MI300X | B12: Third-party GPU price index (about $7.86 per GPU-hour) | C12: Jul 2026 | D12: Estimate only. Microsoft does not publish this rate as clearly as the NVIDIA SKUs.
A13: Azure disk prices and egress ($0.087/GB after 100 GB free) | B13: azure.microsoft.com/pricing/details/managed-disks; egresscost.com; Azure Retail Prices API summaries | C13: Jun-Aug 2026 | D13: Premium SSD v2 at $0.081/GiB comes from Microsoft's own worked example.
A14: Azure region uplifts (+19% Europe, +30% SE Asia, +33% Australia) | B14: Published regional comparisons of the 8x H100 SKU | C14: 2026 | D14: Approximate and applied to every machine. Check your own region for anything important.
A15: Managed platform uplift (Vertex AI ~26%, Azure ML ~25%) | B15: Vertex AI and Azure ML pricing pages, compared with the raw VM rate for the same machine | C15: Jun 2026 | D15: Worked example: a2-highgpu-8g at $33.07/hr on Vertex AI vs $26.27/hr raw.
... A22: Model memory rule of thumb | B22: Standard practice: parameters x bytes per parameter, plus headroom for the KV cache | C22: - | D22: 2 bytes at FP16, 1 at FP8/INT8, 0.5 at INT4. Headroom default 30%.
A25: What changed from the source archive you supplied
A26: - Added Microsoft Azure. The archive priced Google Cloud only.
A27: - Added the GPU tiers the archive was missing: T4 at the bottom, and H200, MI300X and B200 at the top. The archive covered only A100, H100 and L4.
A28: - Fixed the disk prices in the archive's code. It used $0.020/GB for standard and $0.040/GB for balanced; the published rates are $0.040 and $0.100. Balanced was under-costed by 60%.
A29: - Kept the archive's egress tiers ($0.12 / $0.11 / $0.08) - they are still correct - and added the free allowance each cloud gives, which the archive ignored.
A30: - Replaced the 'pick the first GPU that fits' logic with 'pick the cheapest that fits', across both clouds.
A31: - Added the region uplift, spot and commitment pricing, and the managed-platform uplift, none of which the archive priced.
A32: - Added step 7: pay-per-token pricing for 21 hosted models from Google, OpenAI and Anthropic on both clouds, so the workbook now answers build-vs-buy rather than only build.
A33: - Added support and labour cost at $116 per hour, with a Low / Medium / High level recommended from the model size and fully editable. The archive priced hardware only.
A34: - Corrected a bug in the archive's code: filter_instances.py passed the minimum GPU memory into the disk cost function, so storage was priced off GPU memory rather than disk size.
